{
  "avg": {
    "106": [
      "11650.504"
    ], 
    "110": [
      "11634.514"
    ], 
    "116": [
      "11634.504"
    ], 
    "118": [
      "11634.524"
    ], 
    "121": [
      "11634.508"
    ], 
    "133": [
      "11650.508"
    ], 
    "137": [
      "10824.514"
    ], 
    "159": [
      "12434.508", 
      "12434.524"
    ], 
    "161": [
      "12450.508"
    ], 
    "166": [
      "12434.504"
    ], 
    "169": [
      "12450.504"
    ], 
    "182": [
      "10842.508"
    ], 
    "190": [
      "10824.524"
    ], 
    "192": [
      "12434.514"
    ], 
    "210": [
      "10842.504"
    ], 
    "217": [
      "10824.508"
    ], 
    "221": [
      "11650.507"
    ], 
    "225": [
      "11634.502"
    ], 
    "226": [
      "11634.512"
    ], 
    "235": [
      "11634.523", 
      "136.888522"
    ], 
    "248": [
      "10824.504"
    ], 
    "251": [
      "11634.587"
    ], 
    "253": [
      "136.885522"
    ], 
    "254": [
      "11634.522"
    ], 
    "256": [
      "10824.512", 
      "11634.586"
    ], 
    "259": [
      "11634.513"
    ], 
    "260": [
      "11634.503"
    ], 
    "264": [
      "11650.506"
    ], 
    "265": [
      "10824.522"
    ], 
    "271": [
      "11634.583"
    ], 
    "272": [
      "12434.507"
    ], 
    "275": [
      "11634.507"
    ], 
    "280": [
      "12450.506"
    ], 
    "283": [
      "11650.502"
    ], 
    "284": [
      "11634.506"
    ], 
    "286": [
      "136.885512"
    ], 
    "296": [
      "140.065512"
    ], 
    "300": [
      "12434.503"
    ], 
    "301": [
      "12434.513"
    ], 
    "304": [
      "136.888512", 
      "12434.522"
    ], 
    "306": [
      "12434.502", 
      "12450.507"
    ], 
    "309": [
      "10842.502"
    ], 
    "310": [
      "12434.512", 
      "11650.503"
    ], 
    "311": [
      "12434.506", 
      "12434.523"
    ], 
    "312": [
      "12434.583"
    ], 
    "313": [
      "12434.582"
    ], 
    "317": [
      "12450.502"
    ], 
    "318": [
      "10824.513"
    ], 
    "325": [
      "140.065506"
    ], 
    "326": [
      "140.065522"
    ], 
    "333": [
      "10824.523"
    ], 
    "337": [
      "136.888502"
    ], 
    "338": [
      "11634.582"
    ], 
    "345": [
      "136.885502"
    ], 
    "364": [
      "10842.507"
    ], 
    "375": [
      "10842.506"
    ], 
    "376": [
      "12450.503"
    ], 
    "378": [
      "10824.583"
    ], 
    "383": [
      "10824.502"
    ], 
    "384": [
      "10824.507", 
      "10842.503", 
      "10824.582"
    ], 
    "393": [
      "10824.503"
    ], 
    "398": [
      "10824.587"
    ], 
    "399": [
      "10824.506"
    ], 
    "403": [
      "10824.586"
    ], 
    "413": [
      "12434.587"
    ], 
    "425": [
      "12434.586"
    ], 
    "507": [
      "11634.597"
    ], 
    "522": [
      "11634.592"
    ], 
    "527": [
      "11634.593"
    ], 
    "545": [
      "12434.596", 
      "11634.596"
    ], 
    "563": [
      "12434.592"
    ], 
    "612": [
      "10824.593"
    ], 
    "627": [
      "10824.592"
    ], 
    "635": [
      "10824.596"
    ], 
    "636": [
      "10824.597"
    ], 
    "664": [
      "12434.593"
    ], 
    "730": [
      "12434.597"
    ]
  }, 
  "workflows": {
    "10824.502": [
      383, 
      384
    ], 
    "10824.503": [
      430, 
      357
    ], 
    "10824.504": [
      238, 
      258
    ], 
    "10824.506": [
      409, 
      389
    ], 
    "10824.507": [
      352, 
      416
    ], 
    "10824.508": [
      209, 
      226
    ], 
    "10824.512": [
      252, 
      261
    ], 
    "10824.513": [
      326, 
      310
    ], 
    "10824.514": [
      137
    ], 
    "10824.522": [
      266, 
      264
    ], 
    "10824.523": [
      348, 
      318
    ], 
    "10824.524": [
      207, 
      174
    ], 
    "10824.582": [
      348, 
      420
    ], 
    "10824.583": [
      363, 
      394
    ], 
    "10824.586": [
      373, 
      433
    ], 
    "10824.587": [
      358, 
      439
    ], 
    "10824.592": [
      623, 
      631
    ], 
    "10824.593": [
      639, 
      586
    ], 
    "10824.596": [
      617, 
      654
    ], 
    "10824.597": [
      699, 
      573
    ], 
    "10842.502": [
      309, 
      309
    ], 
    "10842.503": [
      418, 
      351
    ], 
    "10842.504": [
      228, 
      193
    ], 
    "10842.506": [
      353, 
      398
    ], 
    "10842.507": [
      350, 
      379
    ], 
    "10842.508": [
      170, 
      195
    ], 
    "11634.502": [
      212, 
      239
    ], 
    "11634.503": [
      255, 
      266
    ], 
    "11634.504": [
      128, 
      105
    ], 
    "11634.506": [
      256, 
      313
    ], 
    "11634.507": [
      244, 
      307
    ], 
    "11634.508": [
      104, 
      138
    ], 
    "11634.512": [
      226, 
      226
    ], 
    "11634.513": [
      250, 
      268
    ], 
    "11634.514": [
      113, 
      108
    ], 
    "11634.522": [
      256, 
      252
    ], 
    "11634.523": [
      241, 
      229
    ], 
    "11634.524": [
      91, 
      146
    ], 
    "11634.582": [
      340, 
      336
    ], 
    "11634.583": [
      285, 
      258
    ], 
    "11634.586": [
      270, 
      243
    ], 
    "11634.587": [
      260, 
      243
    ], 
    "11634.592": [
      509, 
      536
    ], 
    "11634.593": [
      535, 
      519
    ], 
    "11634.596": [
      514, 
      577
    ], 
    "11634.597": [
      506, 
      508
    ], 
    "11650.502": [
      284, 
      283
    ], 
    "11650.503": [
      330, 
      291
    ], 
    "11650.504": [
      105, 
      107
    ], 
    "11650.506": [
      244, 
      285
    ], 
    "11650.507": [
      225, 
      218
    ], 
    "11650.508": [
      128, 
      138
    ], 
    "12434.502": [
      302, 
      310
    ], 
    "12434.503": [
      302, 
      299
    ], 
    "12434.504": [
      166
    ], 
    "12434.506": [
      306, 
      317
    ], 
    "12434.507": [
      262, 
      283
    ], 
    "12434.508": [
      159
    ], 
    "12434.512": [
      298, 
      322
    ], 
    "12434.513": [
      285, 
      318
    ], 
    "12434.514": [
      182, 
      202
    ], 
    "12434.522": [
      307, 
      302
    ], 
    "12434.523": [
      303, 
      320
    ], 
    "12434.524": [
      159
    ], 
    "12434.582": [
      297, 
      330
    ], 
    "12434.583": [
      318, 
      306
    ], 
    "12434.586": [
      413, 
      437
    ], 
    "12434.587": [
      396, 
      431
    ], 
    "12434.592": [
      532, 
      594
    ], 
    "12434.593": [
      669, 
      659
    ], 
    "12434.596": [
      530, 
      560
    ], 
    "12434.597": [
      749, 
      711
    ], 
    "12450.502": [
      315, 
      319
    ], 
    "12450.503": [
      355, 
      398
    ], 
    "12450.504": [
      169
    ], 
    "12450.506": [
      280
    ], 
    "12450.507": [
      293, 
      320
    ], 
    "12450.508": [
      161
    ], 
    "136.885502": [
      323, 
      367
    ], 
    "136.885512": [
      256, 
      316
    ], 
    "136.885522": [
      239, 
      268
    ], 
    "136.888502": [
      357, 
      317
    ], 
    "136.888512": [
      313, 
      296
    ], 
    "136.888522": [
      226, 
      244
    ], 
    "140.065506": [
      341, 
      309
    ], 
    "140.065512": [
      293, 
      299
    ], 
    "140.065522": [
      321, 
      332
    ]
  }
}
