{
  "avg": {
    "63": [
      "135.8"
    ], 
    "77": [
      "2018.8"
    ], 
    "78": [
      "508.0"
    ], 
    "82": [
      "531.0"
    ], 
    "85": [
      "561.0"
    ], 
    "87": [
      "577.0", 
      "102.0"
    ], 
    "91": [
      "2017.8", 
      "250399.0"
    ], 
    "93": [
      "576.0", 
      "509.0"
    ], 
    "95": [
      "101.0"
    ], 
    "98": [
      "1052.1"
    ], 
    "99": [
      "560.0", 
      "545.0"
    ], 
    "101": [
      "1043.0"
    ], 
    "102": [
      "504.0", 
      "574.0"
    ], 
    "103": [
      "505.0"
    ], 
    "105": [
      "570.0"
    ], 
    "108": [
      "250399.17"
    ], 
    "110": [
      "571.0"
    ], 
    "111": [
      "136.7802"
    ], 
    "112": [
      "250399.18"
    ], 
    "114": [
      "506.0", 
      "541.0"
    ], 
    "115": [
      "124.1"
    ], 
    "119": [
      "1045.0"
    ], 
    "121": [
      "1010.0"
    ], 
    "123": [
      "573.0"
    ], 
    "124": [
      "124.2"
    ], 
    "126": [
      "123.1"
    ], 
    "128": [
      "572.0", 
      "123.3"
    ], 
    "129": [
      "546.0"
    ], 
    "133": [
      "124.5", 
      "124.4"
    ], 
    "135": [
      "575.0"
    ], 
    "137": [
      "1044.0"
    ], 
    "140": [
      "500199.0", 
      "123.2"
    ], 
    "147": [
      "1041.0"
    ], 
    "148": [
      "5.4"
    ], 
    "151": [
      "124.6"
    ], 
    "156": [
      "136.7801"
    ], 
    "157": [
      "135.13"
    ], 
    "161": [
      "1040.1"
    ], 
    "162": [
      "5.5"
    ], 
    "166": [
      "2018.13", 
      "1020.0"
    ], 
    "169": [
      "136.885521"
    ], 
    "170": [
      "536.0", 
      "562.0"
    ], 
    "171": [
      "1042.0"
    ], 
    "173": [
      "136.885511"
    ], 
    "175": [
      "5.2"
    ], 
    "181": [
      "136.888511"
    ], 
    "182": [
      "535.0", 
      "2017.13"
    ], 
    "190": [
      "136.7803"
    ], 
    "191": [
      "5.1"
    ], 
    "194": [
      "136.885501"
    ], 
    "196": [
      "5.7"
    ], 
    "197": [
      "136.7611"
    ], 
    "199": [
      "5.3"
    ], 
    "201": [
      "1052.0"
    ], 
    "208": [
      "136.8311"
    ], 
    "209": [
      "105.0"
    ], 
    "214": [
      "138.4"
    ], 
    "215": [
      "5.6", 
      "1325.51", 
      "136.8885"
    ], 
    "216": [
      "140.5611"
    ], 
    "217": [
      "1325.5"
    ], 
    "219": [
      "136.897"
    ], 
    "221": [
      "136.7721"
    ], 
    "229": [
      "136.72411", 
      "1325.516"
    ], 
    "230": [
      "158.01"
    ], 
    "231": [
      "159.01"
    ], 
    "233": [
      "136.8855"
    ], 
    "239": [
      "136.72412"
    ], 
    "242": [
      "136.733"
    ], 
    "244": [
      "138.2", 
      "136.76111", 
      "140.51"
    ], 
    "246": [
      "11634.511"
    ], 
    "248": [
      "136.77211"
    ], 
    "249": [
      "2017.4"
    ], 
    "250": [
      "1325.517"
    ], 
    "255": [
      "136.888501", 
      "11634.505"
    ], 
    "256": [
      "1003.0", 
      "2017.1"
    ], 
    "258": [
      "136.83111", 
      "140.117"
    ], 
    "261": [
      "136.88811", 
      "1325.5161"
    ], 
    "262": [
      "138.1", 
      "25407.0"
    ], 
    "267": [
      "140.57"
    ], 
    "268": [
      "136.888521"
    ], 
    "270": [
      "140.54"
    ], 
    "271": [
      "2017.7", 
      "2018.11"
    ], 
    "275": [
      "25406.0"
    ], 
    "277": [
      "551.0"
    ], 
    "278": [
      "2018.12"
    ], 
    "282": [
      "2018.4"
    ], 
    "284": [
      "136.899"
    ], 
    "285": [
      "1325.1"
    ], 
    "286": [
      "4.22"
    ], 
    "290": [
      "135.5"
    ], 
    "292": [
      "250402.1"
    ], 
    "295": [
      "135.6", 
      "250402.171"
    ], 
    "301": [
      "2017.12"
    ], 
    "303": [
      "2017.9"
    ], 
    "304": [
      "135.4"
    ], 
    "305": [
      "25408.0"
    ], 
    "308": [
      "135.7"
    ], 
    "311": [
      "2018.5"
    ], 
    "313": [
      "1325.518"
    ], 
    "314": [
      "1002.0"
    ], 
    "323": [
      "2018.3", 
      "250408.0"
    ], 
    "325": [
      "2018.7"
    ], 
    "327": [
      "11650.505"
    ], 
    "330": [
      "534.0"
    ], 
    "331": [
      "11634.521"
    ], 
    "335": [
      "2017.3", 
      "2017.11", 
      "250405.0"
    ], 
    "336": [
      "250403.0"
    ], 
    "337": [
      "250406.0"
    ], 
    "339": [
      "11634.5"
    ], 
    "342": [
      "2018.9", 
      "250402.0"
    ], 
    "349": [
      "13234.0"
    ], 
    "356": [
      "250403.17"
    ], 
    "358": [
      "250407.0"
    ], 
    "359": [
      "250402.18"
    ], 
    "360": [
      "11650.501"
    ], 
    "362": [
      "250409.0"
    ], 
    "363": [
      "7.24"
    ], 
    "365": [
      "1323.0", 
      "135.3"
    ], 
    "367": [
      "106.0", 
      "1345.0"
    ], 
    "368": [
      "1348.0"
    ], 
    "369": [
      "1366.0"
    ], 
    "370": [
      "1321.0"
    ], 
    "372": [
      "2018.2", 
      "136.735", 
      "25409.17"
    ], 
    "374": [
      "2500.6", 
      "134.0", 
      "115.0"
    ], 
    "375": [
      "1314.0"
    ], 
    "376": [
      "20834.5"
    ], 
    "377": [
      "250400.17"
    ], 
    "378": [
      "2018.1"
    ], 
    "380": [
      "1002.3", 
      "11634.501"
    ], 
    "382": [
      "7.0"
    ], 
    "383": [
      "1325.4"
    ], 
    "384": [
      "135.2"
    ], 
    "385": [
      "250400.0"
    ], 
    "386": [
      "2018.6"
    ], 
    "388": [
      "135.9"
    ], 
    "390": [
      "2017.6", 
      "158.3", 
      "7.23", 
      "111.0"
    ], 
    "391": [
      "250407.18"
    ], 
    "393": [
      "250402.181", 
      "250409.17"
    ], 
    "394": [
      "1354.0"
    ], 
    "396": [
      "250408.17", 
      "250407.17", 
      "1339.0"
    ], 
    "397": [
      "1364.0"
    ], 
    "398": [
      "1336.0", 
      "119.0"
    ], 
    "399": [
      "135.11"
    ], 
    "400": [
      "250406.18", 
      "1343.0"
    ], 
    "401": [
      "250400.18", 
      "131.0"
    ], 
    "403": [
      "2017.5", 
      "113.0", 
      "1309.0", 
      "4008.0"
    ], 
    "404": [
      "136.8562"
    ], 
    "405": [
      "250406.17", 
      "127.0", 
      "1351.0"
    ], 
    "406": [
      "112.0", 
      "1332.0"
    ], 
    "410": [
      "130.0"
    ], 
    "411": [
      "250409.18", 
      "20834.502"
    ], 
    "412": [
      "135.1"
    ], 
    "413": [
      "1310.0"
    ], 
    "414": [
      "144.6", 
      "250403.18", 
      "13.0", 
      "523.0", 
      "129.0"
    ], 
    "417": [
      "140.52"
    ], 
    "418": [
      "1325.2"
    ], 
    "419": [
      "1001.3"
    ], 
    "422": [
      "134.912", 
      "1344.0", 
      "1.0", 
      "250405.17", 
      "1313.0"
    ], 
    "423": [
      "126.0", 
      "1337.0"
    ], 
    "424": [
      "136.8561"
    ], 
    "425": [
      "10424.0"
    ], 
    "426": [
      "1340.0", 
      "4.6"
    ], 
    "427": [
      "25400.0"
    ], 
    "428": [
      "136.815", 
      "2017.2", 
      "139902.0"
    ], 
    "430": [
      "7.1"
    ], 
    "431": [
      "1324.0", 
      "20834.501"
    ], 
    "432": [
      "132.0"
    ], 
    "434": [
      "134.91"
    ], 
    "435": [
      "11634.1"
    ], 
    "437": [
      "139901.0", 
      "135.12"
    ], 
    "439": [
      "1306.0", 
      "122.0", 
      "250405.18"
    ], 
    "441": [
      "4.43"
    ], 
    "443": [
      "134.801", 
      "250402.17"
    ], 
    "445": [
      "10806.0"
    ], 
    "446": [
      "250408.18", 
      "138.5"
    ], 
    "449": [
      "1315.0"
    ], 
    "450": [
      "110.0", 
      "1349.0"
    ], 
    "452": [
      "103.0", 
      "1355.0"
    ], 
    "454": [
      "1320.0"
    ], 
    "455": [
      "11224.0", 
      "4.44"
    ], 
    "456": [
      "4.36", 
      "27.0", 
      "21061.97"
    ], 
    "457": [
      "158.1"
    ], 
    "458": [
      "134.901", 
      "4.23"
    ], 
    "460": [
      "4.27"
    ], 
    "461": [
      "158.2", 
      "7.3"
    ], 
    "462": [
      "1347.0"
    ], 
    "463": [
      "25406.17"
    ], 
    "465": [
      "4.71", 
      "4007.0", 
      "108.0"
    ], 
    "466": [
      "25406.18"
    ], 
    "467": [
      "4.34", 
      "4.25"
    ], 
    "468": [
      "50200.0", 
      "1350.0"
    ], 
    "469": [
      "136.791", 
      "1333.0"
    ], 
    "470": [
      "136.882"
    ], 
    "471": [
      "134.812"
    ], 
    "474": [
      "4.24"
    ], 
    "475": [
      "1335.0"
    ], 
    "476": [
      "4.26"
    ], 
    "477": [
      "120.0"
    ], 
    "479": [
      "205.0", 
      "4.4"
    ], 
    "480": [
      "136.803", 
      "1317.0"
    ], 
    "481": [
      "1334.0"
    ], 
    "483": [
      "2500.51"
    ], 
    "484": [
      "136.858", 
      "1338.0", 
      "1331.0"
    ], 
    "485": [
      "139.004", 
      "25204.0"
    ], 
    "486": [
      "1352.0", 
      "2500.501"
    ], 
    "487": [
      "134.99602"
    ], 
    "488": [
      "7.4", 
      "1311.0", 
      "1353.0"
    ], 
    "489": [
      "4.37", 
      "4001.0"
    ], 
    "490": [
      "280.0"
    ], 
    "491": [
      "1326.0", 
      "4.58"
    ], 
    "492": [
      "140.0", 
      "25214.0", 
      "145.0"
    ], 
    "494": [
      "200.0"
    ], 
    "496": [
      "136.798", 
      "50207.0"
    ], 
    "500": [
      "7.21"
    ], 
    "501": [
      "128.0", 
      "159.4"
    ], 
    "502": [
      "2500.5", 
      "202.0"
    ], 
    "504": [
      "250207.0", 
      "1004.0"
    ], 
    "506": [
      "159.2"
    ], 
    "507": [
      "1330.0"
    ], 
    "509": [
      "2500.601"
    ], 
    "510": [
      "10003.0"
    ], 
    "511": [
      "136.87", 
      "4006.0"
    ], 
    "512": [
      "4.17"
    ], 
    "513": [
      "50206.0"
    ], 
    "514": [
      "11646.0"
    ], 
    "515": [
      "136.839"
    ], 
    "516": [
      "1318.0", 
      "136.827", 
      "25202.2"
    ], 
    "517": [
      "203.0"
    ], 
    "519": [
      "10808.0"
    ], 
    "520": [
      "11224.6"
    ], 
    "521": [
      "10002.0", 
      "4.29"
    ], 
    "524": [
      "134.71"
    ], 
    "525": [
      "7.22"
    ], 
    "526": [
      "159.1"
    ], 
    "532": [
      "1325.91"
    ], 
    "533": [
      "2500.401", 
      "2500.511"
    ], 
    "534": [
      "513.0"
    ], 
    "536": [
      "136.794"
    ], 
    "537": [
      "2500.4", 
      "1322.0"
    ], 
    "538": [
      "159.3"
    ], 
    "539": [
      "20834.21"
    ], 
    "541": [
      "1001.2"
    ], 
    "544": [
      "10804.0"
    ], 
    "545": [
      "2500.31"
    ], 
    "548": [
      "158.0"
    ], 
    "549": [
      "1325.9"
    ], 
    "550": [
      "1329.0"
    ], 
    "552": [
      "25200.0"
    ], 
    "555": [
      "136.875"
    ], 
    "557": [
      "50204.0"
    ], 
    "558": [
      "10059.0", 
      "136.895"
    ], 
    "559": [
      "1341.0"
    ], 
    "562": [
      "140.001"
    ], 
    "563": [
      "25206.0"
    ], 
    "564": [
      "13992501.0"
    ], 
    "565": [
      "50205.0", 
      "136.873"
    ], 
    "566": [
      "1000.0"
    ], 
    "569": [
      "140.004"
    ], 
    "570": [
      "136.888"
    ], 
    "573": [
      "25202.1"
    ], 
    "574": [
      "50202.0", 
      "50203.0"
    ], 
    "576": [
      "140.003"
    ], 
    "577": [
      "136.891"
    ], 
    "582": [
      "149.0"
    ], 
    "583": [
      "10803.0", 
      "136.878"
    ], 
    "585": [
      "25207.0"
    ], 
    "587": [
      "139.003"
    ], 
    "588": [
      "140.008", 
      "13992502.0"
    ], 
    "589": [
      "25209.0", 
      "34.0"
    ], 
    "590": [
      "10824.8", 
      "10826.0"
    ], 
    "592": [
      "10001.0", 
      "1316.0", 
      "10224.15"
    ], 
    "593": [
      "136.879"
    ], 
    "596": [
      "25215.0", 
      "139.001"
    ], 
    "597": [
      "300.0", 
      "10825.0"
    ], 
    "599": [
      "136.859"
    ], 
    "600": [
      "204.0", 
      "140.56"
    ], 
    "601": [
      "281.0"
    ], 
    "604": [
      "136.867", 
      "136.866"
    ], 
    "605": [
      "301.0"
    ], 
    "606": [
      "136.76"
    ], 
    "608": [
      "50208.0", 
      "136.826", 
      "139.002"
    ], 
    "609": [
      "1370.0"
    ], 
    "610": [
      "140.002", 
      "136.818", 
      "11605.0"
    ], 
    "611": [
      "136.885"
    ], 
    "615": [
      "140.011"
    ], 
    "617": [
      "136.816", 
      "12034.0"
    ], 
    "618": [
      "11634.601"
    ], 
    "619": [
      "136.758"
    ], 
    "620": [
      "11630.0"
    ], 
    "621": [
      "136.862", 
      "11723.17"
    ], 
    "624": [
      "2500.312"
    ], 
    "625": [
      "140.01", 
      "136.764", 
      "11634.24"
    ], 
    "626": [
      "140.005"
    ], 
    "627": [
      "140.006"
    ], 
    "630": [
      "136.861"
    ], 
    "631": [
      "140.009"
    ], 
    "633": [
      "11634.7"
    ], 
    "634": [
      "136.865", 
      "11602.0"
    ], 
    "635": [
      "11834.24", 
      "1325.0"
    ], 
    "636": [
      "11024.0", 
      "150.0"
    ], 
    "637": [
      "11601.0", 
      "310.0", 
      "25208.0"
    ], 
    "638": [
      "136.819", 
      "136.762"
    ], 
    "641": [
      "250205.0"
    ], 
    "646": [
      "311.0"
    ], 
    "649": [
      "10805.0", 
      "140.021"
    ], 
    "650": [
      "11608.0", 
      "250205.17"
    ], 
    "651": [
      "136.82"
    ], 
    "653": [
      "11640.0"
    ], 
    "655": [
      "25205.0", 
      "136.834"
    ], 
    "658": [
      "11603.0"
    ], 
    "662": [
      "136.8642"
    ], 
    "663": [
      "10824.0"
    ], 
    "664": [
      "11607.0", 
      "140.007"
    ], 
    "666": [
      "11650.914", 
      "4.28"
    ], 
    "668": [
      "250204.17"
    ], 
    "670": [
      "11634.0"
    ], 
    "671": [
      "25202.15", 
      "10008.0"
    ], 
    "674": [
      "159.02", 
      "136.869"
    ], 
    "675": [
      "537.0"
    ], 
    "676": [
      "12434.0"
    ], 
    "677": [
      "136.833"
    ], 
    "678": [
      "11606.0"
    ], 
    "680": [
      "250202.0", 
      "25202.0"
    ], 
    "682": [
      "11643.0"
    ], 
    "686": [
      "136.876"
    ], 
    "691": [
      "250206.0"
    ], 
    "692": [
      "136.835"
    ], 
    "694": [
      "11609.0"
    ], 
    "695": [
      "11634.914", 
      "140.03"
    ], 
    "698": [
      "2500.311"
    ], 
    "705": [
      "312.0", 
      "250204.0"
    ], 
    "706": [
      "136.761", 
      "136.824"
    ], 
    "707": [
      "11604.0"
    ], 
    "714": [
      "10005.0", 
      "10859.0", 
      "1360.0"
    ], 
    "716": [
      "159.0"
    ], 
    "718": [
      "302.0", 
      "136.836"
    ], 
    "722": [
      "136.831"
    ], 
    "726": [
      "250200.0"
    ], 
    "732": [
      "11634.91"
    ], 
    "736": [
      "11650.0"
    ], 
    "740": [
      "10225.0"
    ], 
    "742": [
      "10224.0"
    ], 
    "747": [
      "25211.0"
    ], 
    "749": [
      "1362.0", 
      "136.842"
    ], 
    "752": [
      "11634.15", 
      "140.068"
    ], 
    "757": [
      "20834.103"
    ], 
    "759": [
      "11834.0", 
      "20896.0", 
      "20834.75"
    ], 
    "761": [
      "1001.0"
    ], 
    "764": [
      "12834.0"
    ], 
    "767": [
      "12634.99"
    ], 
    "770": [
      "10804.31"
    ], 
    "774": [
      "12634.0", 
      "11834.19"
    ], 
    "777": [
      "11846.0"
    ], 
    "778": [
      "20900.0"
    ], 
    "783": [
      "25212.0"
    ], 
    "784": [
      "13034.0"
    ], 
    "788": [
      "140.069"
    ], 
    "789": [
      "11846.19"
    ], 
    "803": [
      "136.871"
    ], 
    "804": [
      "136.832"
    ], 
    "806": [
      "20834.0", 
      "250202.172"
    ], 
    "814": [
      "20834.9"
    ], 
    "815": [
      "10805.31"
    ], 
    "821": [
      "11025.0"
    ], 
    "836": [
      "250202.2"
    ], 
    "843": [
      "250202.17"
    ], 
    "852": [
      "23634.0"
    ], 
    "870": [
      "1363.0"
    ], 
    "885": [
      "250206.17"
    ], 
    "896": [
      "21034.999", 
      "24034.0"
    ], 
    "923": [
      "511.0"
    ], 
    "929": [
      "250202.4"
    ], 
    "933": [
      "11634.911"
    ], 
    "959": [
      "22434.0"
    ], 
    "961": [
      "20034.0"
    ], 
    "988": [
      "22034.0"
    ], 
    "1003": [
      "23234.0"
    ], 
    "1028": [
      "24434.0"
    ], 
    "1193": [
      "529.0"
    ], 
    "1383": [
      "136.9"
    ], 
    "1464": [
      "138.3"
    ], 
    "2045": [
      "528.0"
    ], 
    "2244": [
      "159.03"
    ], 
    "2932": [
      "525.0"
    ], 
    "2940": [
      "519.0"
    ], 
    "2954": [
      "521.0"
    ], 
    "3208": [
      "518.0"
    ], 
    "3266": [
      "547.0"
    ], 
    "3917": [
      "20834.911"
    ], 
    "3988": [
      "516.0"
    ], 
    "4026": [
      "538.0"
    ], 
    "4045": [
      "512.0"
    ], 
    "4063": [
      "526.0"
    ], 
    "4079": [
      "515.0"
    ], 
    "4884": [
      "158.5"
    ]
  }, 
  "workflows": {
    "1.0": [
      422
    ], 
    "1000.0": [
      566
    ], 
    "10001.0": [
      592
    ], 
    "10002.0": [
      521
    ], 
    "10003.0": [
      510
    ], 
    "10005.0": [
      714
    ], 
    "10008.0": [
      671
    ], 
    "1001.0": [
      761
    ], 
    "1001.2": [
      541
    ], 
    "1001.3": [
      419
    ], 
    "1002.0": [
      314
    ], 
    "1002.3": [
      380
    ], 
    "1003.0": [
      256
    ], 
    "1004.0": [
      504
    ], 
    "10059.0": [
      558
    ], 
    "101.0": [
      95
    ], 
    "1010.0": [
      121
    ], 
    "102.0": [
      87
    ], 
    "1020.0": [
      166
    ], 
    "10224.0": [
      742
    ], 
    "10224.15": [
      592
    ], 
    "10225.0": [
      740
    ], 
    "103.0": [
      452
    ], 
    "1040.1": [
      161
    ], 
    "1041.0": [
      147
    ], 
    "1042.0": [
      171
    ], 
    "10424.0": [
      425
    ], 
    "1043.0": [
      101
    ], 
    "1044.0": [
      137
    ], 
    "1045.0": [
      119
    ], 
    "105.0": [
      209
    ], 
    "1052.0": [
      201
    ], 
    "1052.1": [
      98
    ], 
    "106.0": [
      367
    ], 
    "108.0": [
      465
    ], 
    "10803.0": [
      583
    ], 
    "10804.0": [
      544
    ], 
    "10804.31": [
      770
    ], 
    "10805.0": [
      649
    ], 
    "10805.31": [
      815
    ], 
    "10806.0": [
      445
    ], 
    "10808.0": [
      519
    ], 
    "10824.0": [
      663
    ], 
    "10824.8": [
      590
    ], 
    "10825.0": [
      597
    ], 
    "10826.0": [
      590
    ], 
    "10859.0": [
      714
    ], 
    "110.0": [
      450
    ], 
    "11024.0": [
      636
    ], 
    "11025.0": [
      821
    ], 
    "111.0": [
      390
    ], 
    "112.0": [
      406
    ], 
    "11224.0": [
      455
    ], 
    "11224.6": [
      520
    ], 
    "113.0": [
      403
    ], 
    "115.0": [
      374
    ], 
    "11601.0": [
      637
    ], 
    "11602.0": [
      634
    ], 
    "11603.0": [
      658
    ], 
    "11604.0": [
      707
    ], 
    "11605.0": [
      610
    ], 
    "11606.0": [
      678
    ], 
    "11607.0": [
      664
    ], 
    "11608.0": [
      650
    ], 
    "11609.0": [
      694
    ], 
    "11630.0": [
      620
    ], 
    "11634.0": [
      670
    ], 
    "11634.1": [
      435
    ], 
    "11634.15": [
      752
    ], 
    "11634.24": [
      625
    ], 
    "11634.5": [
      339
    ], 
    "11634.501": [
      380
    ], 
    "11634.505": [
      255
    ], 
    "11634.511": [
      246
    ], 
    "11634.521": [
      331
    ], 
    "11634.601": [
      618
    ], 
    "11634.7": [
      633
    ], 
    "11634.91": [
      732
    ], 
    "11634.911": [
      933
    ], 
    "11634.914": [
      695
    ], 
    "11640.0": [
      653
    ], 
    "11643.0": [
      682
    ], 
    "11646.0": [
      514
    ], 
    "11650.0": [
      736
    ], 
    "11650.501": [
      360
    ], 
    "11650.505": [
      327
    ], 
    "11650.914": [
      666
    ], 
    "11723.17": [
      621
    ], 
    "11834.0": [
      759
    ], 
    "11834.19": [
      774
    ], 
    "11834.24": [
      635
    ], 
    "11846.0": [
      777
    ], 
    "11846.19": [
      789
    ], 
    "119.0": [
      398
    ], 
    "120.0": [
      477
    ], 
    "12034.0": [
      617
    ], 
    "122.0": [
      439
    ], 
    "123.1": [
      126
    ], 
    "123.2": [
      140
    ], 
    "123.3": [
      128
    ], 
    "124.1": [
      115
    ], 
    "124.2": [
      124
    ], 
    "124.4": [
      133
    ], 
    "124.5": [
      133
    ], 
    "124.6": [
      151
    ], 
    "12434.0": [
      676
    ], 
    "126.0": [
      423
    ], 
    "12634.0": [
      774
    ], 
    "12634.99": [
      767
    ], 
    "127.0": [
      405
    ], 
    "128.0": [
      501
    ], 
    "12834.0": [
      764
    ], 
    "129.0": [
      414
    ], 
    "13.0": [
      414
    ], 
    "130.0": [
      410
    ], 
    "13034.0": [
      784
    ], 
    "1306.0": [
      439
    ], 
    "1309.0": [
      403
    ], 
    "131.0": [
      401
    ], 
    "1310.0": [
      413
    ], 
    "1311.0": [
      488
    ], 
    "1313.0": [
      422
    ], 
    "1314.0": [
      375
    ], 
    "1315.0": [
      449
    ], 
    "1316.0": [
      592
    ], 
    "1317.0": [
      480
    ], 
    "1318.0": [
      516
    ], 
    "132.0": [
      432
    ], 
    "1320.0": [
      454
    ], 
    "1321.0": [
      370
    ], 
    "1322.0": [
      537
    ], 
    "1323.0": [
      365
    ], 
    "13234.0": [
      349
    ], 
    "1324.0": [
      431
    ], 
    "1325.0": [
      635
    ], 
    "1325.1": [
      285
    ], 
    "1325.2": [
      418
    ], 
    "1325.4": [
      383
    ], 
    "1325.5": [
      217
    ], 
    "1325.51": [
      215
    ], 
    "1325.516": [
      229
    ], 
    "1325.5161": [
      261
    ], 
    "1325.517": [
      250
    ], 
    "1325.518": [
      313
    ], 
    "1325.9": [
      549
    ], 
    "1325.91": [
      532
    ], 
    "1326.0": [
      491
    ], 
    "1329.0": [
      550
    ], 
    "1330.0": [
      507
    ], 
    "1331.0": [
      484
    ], 
    "1332.0": [
      406
    ], 
    "1333.0": [
      469
    ], 
    "1334.0": [
      481
    ], 
    "1335.0": [
      475
    ], 
    "1336.0": [
      398
    ], 
    "1337.0": [
      423
    ], 
    "1338.0": [
      484
    ], 
    "1339.0": [
      396
    ], 
    "134.0": [
      374
    ], 
    "134.71": [
      524
    ], 
    "134.801": [
      443
    ], 
    "134.812": [
      471
    ], 
    "134.901": [
      458
    ], 
    "134.91": [
      434
    ], 
    "134.912": [
      422
    ], 
    "134.99602": [
      487
    ], 
    "1340.0": [
      426
    ], 
    "1341.0": [
      559
    ], 
    "1343.0": [
      400
    ], 
    "1344.0": [
      422
    ], 
    "1345.0": [
      367
    ], 
    "1347.0": [
      462
    ], 
    "1348.0": [
      368
    ], 
    "1349.0": [
      450
    ], 
    "135.1": [
      412
    ], 
    "135.11": [
      399
    ], 
    "135.12": [
      437
    ], 
    "135.13": [
      157
    ], 
    "135.2": [
      384
    ], 
    "135.3": [
      365
    ], 
    "135.4": [
      304
    ], 
    "135.5": [
      290
    ], 
    "135.6": [
      295
    ], 
    "135.7": [
      308
    ], 
    "135.8": [
      63
    ], 
    "135.9": [
      388
    ], 
    "1350.0": [
      468
    ], 
    "1351.0": [
      405
    ], 
    "1352.0": [
      486
    ], 
    "1353.0": [
      488
    ], 
    "1354.0": [
      394
    ], 
    "1355.0": [
      452
    ], 
    "136.72411": [
      229
    ], 
    "136.72412": [
      239
    ], 
    "136.733": [
      242
    ], 
    "136.735": [
      372
    ], 
    "136.758": [
      619
    ], 
    "136.76": [
      606
    ], 
    "136.761": [
      706
    ], 
    "136.7611": [
      197
    ], 
    "136.76111": [
      244
    ], 
    "136.762": [
      638
    ], 
    "136.764": [
      625
    ], 
    "136.7721": [
      221
    ], 
    "136.77211": [
      248
    ], 
    "136.7801": [
      156
    ], 
    "136.7802": [
      111
    ], 
    "136.7803": [
      190
    ], 
    "136.791": [
      469
    ], 
    "136.794": [
      536
    ], 
    "136.798": [
      496
    ], 
    "136.803": [
      480
    ], 
    "136.815": [
      428
    ], 
    "136.816": [
      617
    ], 
    "136.818": [
      610
    ], 
    "136.819": [
      638
    ], 
    "136.82": [
      651
    ], 
    "136.824": [
      706
    ], 
    "136.826": [
      608
    ], 
    "136.827": [
      516
    ], 
    "136.831": [
      722
    ], 
    "136.8311": [
      208
    ], 
    "136.83111": [
      258
    ], 
    "136.832": [
      804
    ], 
    "136.833": [
      677
    ], 
    "136.834": [
      655
    ], 
    "136.835": [
      692
    ], 
    "136.836": [
      718
    ], 
    "136.839": [
      515
    ], 
    "136.842": [
      749
    ], 
    "136.8561": [
      424
    ], 
    "136.8562": [
      404
    ], 
    "136.858": [
      484
    ], 
    "136.859": [
      599
    ], 
    "136.861": [
      630
    ], 
    "136.862": [
      621
    ], 
    "136.8642": [
      662
    ], 
    "136.865": [
      634
    ], 
    "136.866": [
      604
    ], 
    "136.867": [
      604
    ], 
    "136.869": [
      674
    ], 
    "136.87": [
      511
    ], 
    "136.871": [
      803
    ], 
    "136.873": [
      565
    ], 
    "136.875": [
      555
    ], 
    "136.876": [
      686
    ], 
    "136.878": [
      583
    ], 
    "136.879": [
      593
    ], 
    "136.882": [
      470
    ], 
    "136.885": [
      611
    ], 
    "136.8855": [
      233
    ], 
    "136.885501": [
      194
    ], 
    "136.885511": [
      173
    ], 
    "136.885521": [
      169
    ], 
    "136.888": [
      570
    ], 
    "136.88811": [
      261
    ], 
    "136.8885": [
      215
    ], 
    "136.888501": [
      255
    ], 
    "136.888511": [
      181
    ], 
    "136.888521": [
      268
    ], 
    "136.891": [
      577
    ], 
    "136.895": [
      558
    ], 
    "136.897": [
      219
    ], 
    "136.899": [
      284
    ], 
    "136.9": [
      1383
    ], 
    "1360.0": [
      714
    ], 
    "1362.0": [
      749
    ], 
    "1363.0": [
      870
    ], 
    "1364.0": [
      397
    ], 
    "1366.0": [
      369
    ], 
    "1370.0": [
      609
    ], 
    "138.1": [
      262
    ], 
    "138.2": [
      244
    ], 
    "138.3": [
      1464
    ], 
    "138.4": [
      214
    ], 
    "138.5": [
      446
    ], 
    "139.001": [
      596
    ], 
    "139.002": [
      608
    ], 
    "139.003": [
      587
    ], 
    "139.004": [
      485
    ], 
    "139901.0": [
      437
    ], 
    "139902.0": [
      428
    ], 
    "13992501.0": [
      564
    ], 
    "13992502.0": [
      588
    ], 
    "140.0": [
      492
    ], 
    "140.001": [
      562
    ], 
    "140.002": [
      610
    ], 
    "140.003": [
      576
    ], 
    "140.004": [
      569
    ], 
    "140.005": [
      626
    ], 
    "140.006": [
      627
    ], 
    "140.007": [
      664
    ], 
    "140.008": [
      588
    ], 
    "140.009": [
      631
    ], 
    "140.01": [
      625
    ], 
    "140.011": [
      615
    ], 
    "140.021": [
      649
    ], 
    "140.03": [
      695
    ], 
    "140.068": [
      752
    ], 
    "140.069": [
      788
    ], 
    "140.117": [
      258
    ], 
    "140.51": [
      244
    ], 
    "140.52": [
      417
    ], 
    "140.54": [
      270
    ], 
    "140.56": [
      600
    ], 
    "140.5611": [
      216
    ], 
    "140.57": [
      267
    ], 
    "144.6": [
      414
    ], 
    "145.0": [
      492
    ], 
    "149.0": [
      582
    ], 
    "150.0": [
      636
    ], 
    "158.0": [
      548
    ], 
    "158.01": [
      230
    ], 
    "158.1": [
      457
    ], 
    "158.2": [
      461
    ], 
    "158.3": [
      390
    ], 
    "158.5": [
      4884
    ], 
    "159.0": [
      716
    ], 
    "159.01": [
      231
    ], 
    "159.02": [
      674
    ], 
    "159.03": [
      2244
    ], 
    "159.1": [
      526
    ], 
    "159.2": [
      506
    ], 
    "159.3": [
      538
    ], 
    "159.4": [
      501
    ], 
    "200.0": [
      494
    ], 
    "20034.0": [
      961
    ], 
    "2017.1": [
      256
    ], 
    "2017.11": [
      335
    ], 
    "2017.12": [
      301
    ], 
    "2017.13": [
      182
    ], 
    "2017.2": [
      428
    ], 
    "2017.3": [
      335
    ], 
    "2017.4": [
      249
    ], 
    "2017.5": [
      403
    ], 
    "2017.6": [
      390
    ], 
    "2017.7": [
      271
    ], 
    "2017.8": [
      91
    ], 
    "2017.9": [
      303
    ], 
    "2018.1": [
      378
    ], 
    "2018.11": [
      271
    ], 
    "2018.12": [
      278
    ], 
    "2018.13": [
      166
    ], 
    "2018.2": [
      372
    ], 
    "2018.3": [
      323
    ], 
    "2018.4": [
      282
    ], 
    "2018.5": [
      311
    ], 
    "2018.6": [
      386
    ], 
    "2018.7": [
      325
    ], 
    "2018.8": [
      77
    ], 
    "2018.9": [
      342
    ], 
    "202.0": [
      502
    ], 
    "203.0": [
      517
    ], 
    "204.0": [
      600
    ], 
    "205.0": [
      479
    ], 
    "20834.0": [
      806
    ], 
    "20834.103": [
      757
    ], 
    "20834.21": [
      539
    ], 
    "20834.5": [
      376
    ], 
    "20834.501": [
      431
    ], 
    "20834.502": [
      411
    ], 
    "20834.75": [
      759
    ], 
    "20834.9": [
      814
    ], 
    "20834.911": [
      3917
    ], 
    "20896.0": [
      759
    ], 
    "20900.0": [
      778
    ], 
    "21034.999": [
      896
    ], 
    "21061.97": [
      456
    ], 
    "22034.0": [
      988
    ], 
    "22434.0": [
      959
    ], 
    "23234.0": [
      1003
    ], 
    "23634.0": [
      852
    ], 
    "24034.0": [
      896
    ], 
    "24434.0": [
      1028
    ], 
    "2500.31": [
      545
    ], 
    "2500.311": [
      698
    ], 
    "2500.312": [
      624
    ], 
    "2500.4": [
      537
    ], 
    "2500.401": [
      533
    ], 
    "2500.5": [
      502
    ], 
    "2500.501": [
      486
    ], 
    "2500.51": [
      483
    ], 
    "2500.511": [
      533
    ], 
    "2500.6": [
      374
    ], 
    "2500.601": [
      509
    ], 
    "250200.0": [
      726
    ], 
    "250202.0": [
      680
    ], 
    "250202.17": [
      843
    ], 
    "250202.172": [
      806
    ], 
    "250202.2": [
      836
    ], 
    "250202.4": [
      929
    ], 
    "250204.0": [
      705
    ], 
    "250204.17": [
      668
    ], 
    "250205.0": [
      641
    ], 
    "250205.17": [
      650
    ], 
    "250206.0": [
      691
    ], 
    "250206.17": [
      885
    ], 
    "250207.0": [
      504
    ], 
    "250399.0": [
      91
    ], 
    "250399.17": [
      108
    ], 
    "250399.18": [
      112
    ], 
    "250400.0": [
      385
    ], 
    "250400.17": [
      377
    ], 
    "250400.18": [
      401
    ], 
    "250402.0": [
      342
    ], 
    "250402.1": [
      292
    ], 
    "250402.17": [
      443
    ], 
    "250402.171": [
      295
    ], 
    "250402.18": [
      359
    ], 
    "250402.181": [
      393
    ], 
    "250403.0": [
      336
    ], 
    "250403.17": [
      356
    ], 
    "250403.18": [
      414
    ], 
    "250405.0": [
      335
    ], 
    "250405.17": [
      422
    ], 
    "250405.18": [
      439
    ], 
    "250406.0": [
      337
    ], 
    "250406.17": [
      405
    ], 
    "250406.18": [
      400
    ], 
    "250407.0": [
      358
    ], 
    "250407.17": [
      396
    ], 
    "250407.18": [
      391
    ], 
    "250408.0": [
      323
    ], 
    "250408.17": [
      396
    ], 
    "250408.18": [
      446
    ], 
    "250409.0": [
      362
    ], 
    "250409.17": [
      393
    ], 
    "250409.18": [
      411
    ], 
    "25200.0": [
      552
    ], 
    "25202.0": [
      680
    ], 
    "25202.1": [
      573
    ], 
    "25202.15": [
      671
    ], 
    "25202.2": [
      516
    ], 
    "25204.0": [
      485
    ], 
    "25205.0": [
      655
    ], 
    "25206.0": [
      563
    ], 
    "25207.0": [
      585
    ], 
    "25208.0": [
      637
    ], 
    "25209.0": [
      589
    ], 
    "25211.0": [
      747
    ], 
    "25212.0": [
      783
    ], 
    "25214.0": [
      492
    ], 
    "25215.0": [
      596
    ], 
    "25400.0": [
      427
    ], 
    "25406.0": [
      275
    ], 
    "25406.17": [
      463
    ], 
    "25406.18": [
      466
    ], 
    "25407.0": [
      262
    ], 
    "25408.0": [
      305
    ], 
    "25409.17": [
      372
    ], 
    "27.0": [
      456
    ], 
    "280.0": [
      490
    ], 
    "281.0": [
      601
    ], 
    "300.0": [
      597
    ], 
    "301.0": [
      605
    ], 
    "302.0": [
      718
    ], 
    "310.0": [
      637
    ], 
    "311.0": [
      646
    ], 
    "312.0": [
      705
    ], 
    "34.0": [
      589
    ], 
    "4.17": [
      512
    ], 
    "4.22": [
      286
    ], 
    "4.23": [
      458
    ], 
    "4.24": [
      474
    ], 
    "4.25": [
      467
    ], 
    "4.26": [
      476
    ], 
    "4.27": [
      460
    ], 
    "4.28": [
      666
    ], 
    "4.29": [
      521
    ], 
    "4.34": [
      467
    ], 
    "4.36": [
      456
    ], 
    "4.37": [
      489
    ], 
    "4.4": [
      479
    ], 
    "4.43": [
      441
    ], 
    "4.44": [
      455
    ], 
    "4.58": [
      491
    ], 
    "4.6": [
      426
    ], 
    "4.71": [
      465
    ], 
    "4001.0": [
      489
    ], 
    "4006.0": [
      511
    ], 
    "4007.0": [
      465
    ], 
    "4008.0": [
      403
    ], 
    "5.1": [
      191
    ], 
    "5.2": [
      175
    ], 
    "5.3": [
      199
    ], 
    "5.4": [
      148
    ], 
    "5.5": [
      162
    ], 
    "5.6": [
      215
    ], 
    "5.7": [
      196
    ], 
    "500199.0": [
      140
    ], 
    "50200.0": [
      468
    ], 
    "50202.0": [
      574
    ], 
    "50203.0": [
      574
    ], 
    "50204.0": [
      557
    ], 
    "50205.0": [
      565
    ], 
    "50206.0": [
      513
    ], 
    "50207.0": [
      496
    ], 
    "50208.0": [
      608
    ], 
    "504.0": [
      102
    ], 
    "505.0": [
      103
    ], 
    "506.0": [
      114
    ], 
    "508.0": [
      78
    ], 
    "509.0": [
      93
    ], 
    "511.0": [
      923
    ], 
    "512.0": [
      4045
    ], 
    "513.0": [
      534
    ], 
    "515.0": [
      4079
    ], 
    "516.0": [
      3988
    ], 
    "518.0": [
      3208
    ], 
    "519.0": [
      2940
    ], 
    "521.0": [
      2954
    ], 
    "523.0": [
      414
    ], 
    "525.0": [
      2932
    ], 
    "526.0": [
      4063
    ], 
    "528.0": [
      2045
    ], 
    "529.0": [
      1193
    ], 
    "531.0": [
      82
    ], 
    "534.0": [
      330
    ], 
    "535.0": [
      182
    ], 
    "536.0": [
      170
    ], 
    "537.0": [
      675
    ], 
    "538.0": [
      4026
    ], 
    "541.0": [
      114
    ], 
    "545.0": [
      99
    ], 
    "546.0": [
      129
    ], 
    "547.0": [
      3266
    ], 
    "551.0": [
      277
    ], 
    "560.0": [
      99
    ], 
    "561.0": [
      85
    ], 
    "562.0": [
      170
    ], 
    "570.0": [
      105
    ], 
    "571.0": [
      110
    ], 
    "572.0": [
      128
    ], 
    "573.0": [
      123
    ], 
    "574.0": [
      102
    ], 
    "575.0": [
      135
    ], 
    "576.0": [
      93
    ], 
    "577.0": [
      87
    ], 
    "7.0": [
      382
    ], 
    "7.1": [
      430
    ], 
    "7.21": [
      500
    ], 
    "7.22": [
      525
    ], 
    "7.23": [
      390
    ], 
    "7.24": [
      363
    ], 
    "7.3": [
      461
    ], 
    "7.4": [
      488
    ]
  }
}
