{
  "avg": {
    "61": [
      "135.8"
    ], 
    "70": [
      "506.0"
    ], 
    "71": [
      "1052.1"
    ], 
    "73": [
      "2018.8"
    ], 
    "78": [
      "561.0", 
      "2017.8", 
      "531.0"
    ], 
    "83": [
      "576.0"
    ], 
    "85": [
      "504.0", 
      "545.0", 
      "509.0"
    ], 
    "86": [
      "250399.0"
    ], 
    "87": [
      "541.0"
    ], 
    "90": [
      "577.0", 
      "124.5"
    ], 
    "99": [
      "508.0"
    ], 
    "101": [
      "560.0"
    ], 
    "102": [
      "546.0", 
      "505.0"
    ], 
    "103": [
      "570.0"
    ], 
    "104": [
      "102.0"
    ], 
    "105": [
      "556.0"
    ], 
    "108": [
      "572.0"
    ], 
    "110": [
      "101.0"
    ], 
    "111": [
      "250399.18", 
      "123.2"
    ], 
    "113": [
      "250399.17", 
      "123.3"
    ], 
    "114": [
      "136.7802"
    ], 
    "117": [
      "574.0"
    ], 
    "118": [
      "571.0", 
      "1010.0"
    ], 
    "119": [
      "124.1", 
      "123.1"
    ], 
    "121": [
      "575.0", 
      "1043.0", 
      "524.0"
    ], 
    "122": [
      "500199.0", 
      "140.201", 
      "520.0"
    ], 
    "123": [
      "1045.0"
    ], 
    "124": [
      "517.0"
    ], 
    "125": [
      "536.0"
    ], 
    "126": [
      "124.4"
    ], 
    "129": [
      "514.0"
    ], 
    "133": [
      "1041.0"
    ], 
    "134": [
      "1044.0"
    ], 
    "138": [
      "250199.17"
    ], 
    "139": [
      "136.7801"
    ], 
    "140": [
      "573.0"
    ], 
    "141": [
      "1005.0"
    ], 
    "142": [
      "124.2", 
      "552.0"
    ], 
    "143": [
      "548.0", 
      "1040.1"
    ], 
    "144": [
      "535.0"
    ], 
    "145": [
      "124.6"
    ], 
    "147": [
      "136.888521"
    ], 
    "150": [
      "138.2", 
      "13240.303", 
      "507.0"
    ], 
    "153": [
      "136.8885"
    ], 
    "154": [
      "527.0"
    ], 
    "155": [
      "1052.0"
    ], 
    "160": [
      "5.4"
    ], 
    "161": [
      "136.8855", 
      "10824.511", 
      "140.065511"
    ], 
    "162": [
      "250199.18", 
      "11634.511"
    ], 
    "163": [
      "1020.0"
    ], 
    "164": [
      "250199.0"
    ], 
    "165": [
      "530.0"
    ], 
    "167": [
      "5.5", 
      "11634.521", 
      "10824.521"
    ], 
    "171": [
      "136.899"
    ], 
    "172": [
      "2500.5111", 
      "140.065521", 
      "136.885521"
    ], 
    "176": [
      "136.885501"
    ], 
    "178": [
      "5.1"
    ], 
    "179": [
      "503.0"
    ], 
    "180": [
      "136.888511"
    ], 
    "181": [
      "136.733"
    ], 
    "182": [
      "140.53"
    ], 
    "183": [
      "562.0"
    ], 
    "184": [
      "136.885511"
    ], 
    "186": [
      "551.0", 
      "14040.303", 
      "11634.5"
    ], 
    "187": [
      "5.2", 
      "136.7803"
    ], 
    "192": [
      "105.0"
    ], 
    "195": [
      "5.3"
    ], 
    "197": [
      "136.888501", 
      "5.6", 
      "11650.505"
    ], 
    "198": [
      "138.4", 
      "10824.501", 
      "510.0"
    ], 
    "200": [
      "140.202"
    ], 
    "201": [
      "135.13", 
      "10024.5", 
      "5.7"
    ], 
    "203": [
      "138.1"
    ], 
    "206": [
      "11634.501"
    ], 
    "208": [
      "136.897", 
      "8.0"
    ], 
    "211": [
      "140.6"
    ], 
    "213": [
      "10842.501"
    ], 
    "214": [
      "10824.5", 
      "10842.505"
    ], 
    "218": [
      "2017.13"
    ], 
    "219": [
      "134.813"
    ], 
    "220": [
      "10024.1", 
      "1307.0"
    ], 
    "221": [
      "2018.13"
    ], 
    "224": [
      "1325.3"
    ], 
    "225": [
      "140.5611", 
      "140.065505"
    ], 
    "226": [
      "11634.505", 
      "554.0"
    ], 
    "231": [
      "140.61", 
      "1325.5161"
    ], 
    "234": [
      "10024.3"
    ], 
    "235": [
      "159.01"
    ], 
    "236": [
      "1325.518"
    ], 
    "237": [
      "10824.1"
    ], 
    "239": [
      "11650.501"
    ], 
    "242": [
      "10824.505"
    ], 
    "243": [
      "158.01"
    ], 
    "244": [
      "1030.0"
    ], 
    "247": [
      "136.7611"
    ], 
    "249": [
      "136.77211", 
      "136.8311"
    ], 
    "254": [
      "1302.0"
    ], 
    "257": [
      "250402.1"
    ], 
    "258": [
      "4.22"
    ], 
    "261": [
      "140.57"
    ], 
    "263": [
      "8.1"
    ], 
    "266": [
      "534.0"
    ], 
    "267": [
      "1325.51"
    ], 
    "268": [
      "1325.517", 
      "1325.516"
    ], 
    "273": [
      "522.0"
    ], 
    "275": [
      "1301.17"
    ], 
    "276": [
      "555.0"
    ], 
    "277": [
      "4003.0"
    ], 
    "287": [
      "1308.0", 
      "140.54"
    ], 
    "288": [
      "11634.1"
    ], 
    "289": [
      "25409.0"
    ], 
    "291": [
      "136.88811", 
      "140.51"
    ], 
    "292": [
      "6.0", 
      "136.83111", 
      "136.7721"
    ], 
    "293": [
      "1325.1"
    ], 
    "294": [
      "136.72411"
    ], 
    "295": [
      "19.0"
    ], 
    "297": [
      "250402.181", 
      "1042.0"
    ], 
    "298": [
      "250405.17"
    ], 
    "301": [
      "7.0", 
      "18.0"
    ], 
    "302": [
      "25403.0"
    ], 
    "303": [
      "1003.0", 
      "25405.0"
    ], 
    "304": [
      "250400.18", 
      "250406.0"
    ], 
    "305": [
      "136.76111", 
      "250402.18"
    ], 
    "306": [
      "1304.182", 
      "20.0"
    ], 
    "307": [
      "4000.0", 
      "135.7"
    ], 
    "308": [
      "250408.18", 
      "2.0"
    ], 
    "309": [
      "4002.0"
    ], 
    "310": [
      "2018.2", 
      "17.0", 
      "250403.0"
    ], 
    "311": [
      "25400.18"
    ], 
    "312": [
      "1302.17"
    ], 
    "313": [
      "2017.5"
    ], 
    "314": [
      "13234.0", 
      "523.0", 
      "250407.0"
    ], 
    "315": [
      "250402.0", 
      "138.5"
    ], 
    "317": [
      "25407.18", 
      "250402.171"
    ], 
    "319": [
      "25403.17"
    ], 
    "320": [
      "134.99901"
    ], 
    "321": [
      "25407.17"
    ], 
    "322": [
      "250403.17", 
      "10024.4"
    ], 
    "323": [
      "250409.17"
    ], 
    "324": [
      "250408.17", 
      "134.903"
    ], 
    "326": [
      "250400.0", 
      "250407.17"
    ], 
    "327": [
      "33.0"
    ], 
    "328": [
      "22.0", 
      "25407.0"
    ], 
    "329": [
      "32.0", 
      "25405.17", 
      "1325.5"
    ], 
    "330": [
      "250407.18"
    ], 
    "331": [
      "250200.1"
    ], 
    "332": [
      "2017.9", 
      "134.909"
    ], 
    "333": [
      "16.0", 
      "1304.181", 
      "250402.17"
    ], 
    "334": [
      "2018.7"
    ], 
    "335": [
      "1304.18", 
      "134.91", 
      "1301.0"
    ], 
    "336": [
      "43.0", 
      "134.911", 
      "140.52", 
      "144.6", 
      "250408.0", 
      "2017.12"
    ], 
    "337": [
      "2018.12"
    ], 
    "338": [
      "134.707", 
      "25403.18"
    ], 
    "339": [
      "1.0", 
      "7.24"
    ], 
    "340": [
      "7.2", 
      "141.113", 
      "25406.18"
    ], 
    "341": [
      "14034.0"
    ], 
    "342": [
      "250409.0", 
      "15.0", 
      "134.708"
    ], 
    "343": [
      "250403.18", 
      "109.0", 
      "135.12", 
      "21.0"
    ], 
    "344": [
      "4.72", 
      "25405.18", 
      "122.0"
    ], 
    "345": [
      "136.72412", 
      "25402.0", 
      "1002.0"
    ], 
    "346": [
      "25409.18", 
      "25408.18"
    ], 
    "348": [
      "250400.17", 
      "134.906", 
      "11.0", 
      "1004.0"
    ], 
    "349": [
      "2017.3", 
      "31.0"
    ], 
    "350": [
      "9.0", 
      "117.0", 
      "1325.2", 
      "30.0", 
      "250405.0", 
      "134.703"
    ], 
    "351": [
      "27.0"
    ], 
    "352": [
      "4.74", 
      "24.0", 
      "10.0", 
      "8.2"
    ], 
    "353": [
      "25400.0", 
      "134.902", 
      "20834.501", 
      "23.0"
    ], 
    "354": [
      "2018.3"
    ], 
    "355": [
      "1353.0"
    ], 
    "356": [
      "35.0", 
      "2017.6", 
      "4.42", 
      "135.2", 
      "134.705"
    ], 
    "357": [
      "500200.1", 
      "140.113", 
      "38.0"
    ], 
    "358": [
      "139901.0", 
      "11834.21", 
      "4.53"
    ], 
    "359": [
      "1302.181"
    ], 
    "361": [
      "25402.17", 
      "121.0", 
      "134.803"
    ], 
    "362": [
      "2017.7", 
      "2017.4", 
      "134.904", 
      "4.41"
    ], 
    "363": [
      "4.61", 
      "26.0", 
      "44.0", 
      "2018.11", 
      "1303.0", 
      "29.0"
    ], 
    "364": [
      "132.0", 
      "1314.0", 
      "25408.17"
    ], 
    "365": [
      "2018.9", 
      "25408.0", 
      "1328.0", 
      "7.4", 
      "135.3", 
      "113.0", 
      "250409.18", 
      "134.802"
    ], 
    "366": [
      "7.1", 
      "10024.2"
    ], 
    "367": [
      "37.0", 
      "2500.501", 
      "7.23", 
      "1344.0", 
      "134.809"
    ], 
    "368": [
      "250200.117", 
      "1334.0", 
      "115.0", 
      "25402.18", 
      "4.52", 
      "4.68"
    ], 
    "369": [
      "1351.0"
    ], 
    "371": [
      "4007.0", 
      "134.709", 
      "135.1", 
      "135.14", 
      "1040.0"
    ], 
    "372": [
      "7.3"
    ], 
    "373": [
      "14.0", 
      "4.54", 
      "1315.0"
    ], 
    "374": [
      "134.99603", 
      "1302.18", 
      "116.0", 
      "1311.0", 
      "1325.4"
    ], 
    "375": [
      "25406.0", 
      "130.0", 
      "1306.0", 
      "134.905"
    ], 
    "376": [
      "4.73", 
      "7.22"
    ], 
    "377": [
      "140.005", 
      "250406.17", 
      "158.2", 
      "106.0", 
      "127.0"
    ], 
    "378": [
      "25406.17", 
      "1343.0", 
      "12.0", 
      "118.0", 
      "25400.17", 
      "1319.0", 
      "1313.0"
    ], 
    "379": [
      "114.0", 
      "110.0", 
      "4.62", 
      "1310.0"
    ], 
    "381": [
      "140.0"
    ], 
    "382": [
      "3.0", 
      "134.704"
    ], 
    "383": [
      "2018.1", 
      "1326.0", 
      "134.908", 
      "1349.0"
    ], 
    "384": [
      "500203.0", 
      "129.0"
    ], 
    "385": [
      "500204.0", 
      "1002.3", 
      "21061.97"
    ], 
    "386": [
      "136.729", 
      "134.0", 
      "139.003"
    ], 
    "387": [
      "158.1", 
      "12034.0", 
      "134.804", 
      "119.0"
    ], 
    "388": [
      "134.811", 
      "131.0"
    ], 
    "389": [
      "1327.0", 
      "134.702"
    ], 
    "390": [
      "250406.18", 
      "125.0", 
      "135.6", 
      "134.706"
    ], 
    "391": [
      "45.0", 
      "4.78", 
      "1348.0"
    ], 
    "392": [
      "134.99601", 
      "11834.24", 
      "134.806"
    ], 
    "393": [
      "4.75", 
      "128.0", 
      "28.0"
    ], 
    "394": [
      "2017.2", 
      "4.51", 
      "1335.0"
    ], 
    "395": [
      "134.805", 
      "139902.0", 
      "136.723"
    ], 
    "396": [
      "159.2", 
      "1303.17"
    ], 
    "398": [
      "2017.1", 
      "4.64", 
      "4.67"
    ], 
    "399": [
      "4.55"
    ], 
    "400": [
      "2500.33"
    ], 
    "402": [
      "134.81", 
      "250405.18", 
      "4.24"
    ], 
    "403": [
      "135.9"
    ], 
    "404": [
      "136.778", 
      "1309.0"
    ], 
    "405": [
      "145.0"
    ], 
    "406": [
      "2018.4", 
      "4.25"
    ], 
    "407": [
      "140.002", 
      "136.732", 
      "135.4", 
      "159.1"
    ], 
    "408": [
      "135.5", 
      "25409.17"
    ], 
    "409": [
      "500206.0"
    ], 
    "410": [
      "1316.0"
    ], 
    "411": [
      "500207.0"
    ], 
    "412": [
      "4001.0"
    ], 
    "413": [
      "1350.0"
    ], 
    "414": [
      "4.36"
    ], 
    "415": [
      "1352.0"
    ], 
    "416": [
      "140.009", 
      "1365.0"
    ], 
    "417": [
      "139.001"
    ], 
    "418": [
      "135.11", 
      "140.004", 
      "4.77", 
      "126.0", 
      "140.58", 
      "1002.4"
    ], 
    "419": [
      "1312.0"
    ], 
    "420": [
      "2018.6", 
      "140.003"
    ], 
    "421": [
      "4.76", 
      "11606.0", 
      "111.0"
    ], 
    "422": [
      "4.71", 
      "136.721", 
      "4.45", 
      "136.8562", 
      "1345.0", 
      "4.6"
    ], 
    "423": [
      "11601.0", 
      "158.3", 
      "1339.0", 
      "39.0", 
      "136.722"
    ], 
    "424": [
      "133.0", 
      "4.26", 
      "25204.0"
    ], 
    "425": [
      "1332.0", 
      "1364.0", 
      "103.0"
    ], 
    "426": [
      "500205.0", 
      "11650.0", 
      "11640.0"
    ], 
    "427": [
      "10424.0", 
      "140.023", 
      "1333.0"
    ], 
    "428": [
      "136.731", 
      "250207.0", 
      "136.756", 
      "140.01"
    ], 
    "429": [
      "2018.5", 
      "1354.0", 
      "4.4"
    ], 
    "430": [
      "136.791", 
      "13.0"
    ], 
    "431": [
      "136.745", 
      "2017.11", 
      "1347.0"
    ], 
    "432": [
      "1340.0"
    ], 
    "433": [
      "136.734", 
      "136.73"
    ], 
    "434": [
      "11634.601", 
      "4.63"
    ], 
    "435": [
      "1324.0"
    ], 
    "437": [
      "11224.6", 
      "4.57", 
      "11608.0"
    ], 
    "438": [
      "112.0", 
      "1337.0"
    ], 
    "439": [
      "134.907", 
      "203.0", 
      "20834.502"
    ], 
    "440": [
      "50207.0", 
      "1355.0"
    ], 
    "441": [
      "140.006", 
      "136.813", 
      "14234.0", 
      "20834.21"
    ], 
    "442": [
      "120.0", 
      "200.0", 
      "13434.0", 
      "139.002"
    ], 
    "443": [
      "4.34", 
      "250200.118"
    ], 
    "444": [
      "11634.91", 
      "20834.5"
    ], 
    "445": [
      "281.0", 
      "11634.7", 
      "1366.0", 
      "136.724"
    ], 
    "446": [
      "136.776", 
      "1102.0", 
      "25.0", 
      "136.726"
    ], 
    "447": [
      "140.001", 
      "108.0", 
      "159.3"
    ], 
    "448": [
      "136.894", 
      "4.65"
    ], 
    "449": [
      "1320.0", 
      "4.27"
    ], 
    "450": [
      "136.801", 
      "140.109", 
      "1323.0", 
      "150.0", 
      "159.4"
    ], 
    "452": [
      "312.0"
    ], 
    "453": [
      "134.71", 
      "250206.118", 
      "140.071"
    ], 
    "454": [
      "134.808", 
      "136.735", 
      "136.79"
    ], 
    "455": [
      "140.043", 
      "136.8561", 
      "140.072"
    ], 
    "457": [
      "140.007", 
      "134.912"
    ], 
    "459": [
      "300.0", 
      "10001.0"
    ], 
    "460": [
      "136.742", 
      "134.812"
    ], 
    "461": [
      "136.736", 
      "204.0", 
      "4.43"
    ], 
    "462": [
      "1001.3", 
      "1321.0"
    ], 
    "463": [
      "140.022"
    ], 
    "464": [
      "1329.0"
    ], 
    "465": [
      "140.077"
    ], 
    "466": [
      "10008.0", 
      "136.839"
    ], 
    "467": [
      "136.754"
    ], 
    "468": [
      "140.008", 
      "134.99602", 
      "11630.0"
    ], 
    "469": [
      "11634.15", 
      "7.21", 
      "134.801"
    ], 
    "471": [
      "11603.0", 
      "1336.0"
    ], 
    "472": [
      "10803.0", 
      "136.727", 
      "4.23"
    ], 
    "473": [
      "140.03", 
      "136.846"
    ], 
    "474": [
      "136.803", 
      "4006.0"
    ], 
    "475": [
      "136.769", 
      "10806.0"
    ], 
    "476": [
      "11643.0", 
      "202.0", 
      "136.753"
    ], 
    "478": [
      "500202.0", 
      "11723.17"
    ], 
    "479": [
      "500200.0"
    ], 
    "480": [
      "250203.0", 
      "11602.0", 
      "34.0", 
      "250202.0", 
      "134.807"
    ], 
    "481": [
      "136.771", 
      "134.901", 
      "1370.17", 
      "136.827", 
      "4008.0"
    ], 
    "482": [
      "134.701"
    ], 
    "483": [
      "140.078", 
      "140.076"
    ], 
    "484": [
      "10023.0", 
      "1317.0"
    ], 
    "487": [
      "1341.0"
    ], 
    "488": [
      "4.37", 
      "140.029", 
      "10823.0", 
      "10824.6"
    ], 
    "489": [
      "136.757"
    ], 
    "490": [
      "10801.0"
    ], 
    "491": [
      "136.792"
    ], 
    "492": [
      "11609.0", 
      "136.738", 
      "1338.0", 
      "36.0"
    ], 
    "493": [
      "10808.0", 
      "1318.0", 
      "4.58", 
      "205.0"
    ], 
    "494": [
      "310.0", 
      "136.779", 
      "136.767"
    ], 
    "495": [
      "136.77", 
      "1325.9"
    ], 
    "496": [
      "136.845"
    ], 
    "497": [
      "136.825", 
      "13992501.0", 
      "136.81"
    ], 
    "498": [
      "136.749", 
      "1325.0", 
      "136.849"
    ], 
    "500": [
      "11224.0", 
      "136.802", 
      "136.728"
    ], 
    "501": [
      "1001.0", 
      "50203.0", 
      "136.858"
    ], 
    "502": [
      "1322.0", 
      "10025.0"
    ], 
    "503": [
      "10005.0"
    ], 
    "504": [
      "136.758", 
      "136.815", 
      "140.028", 
      "301.0", 
      "136.87"
    ], 
    "505": [
      "136.765"
    ], 
    "506": [
      "136.748"
    ], 
    "507": [
      "136.772", 
      "136.796", 
      "139.004"
    ], 
    "508": [
      "136.725", 
      "136.752"
    ], 
    "509": [
      "50205.0"
    ], 
    "510": [
      "11604.0"
    ], 
    "511": [
      "11607.0"
    ], 
    "512": [
      "1370.0"
    ], 
    "513": [
      "311.0", 
      "136.737", 
      "10003.0", 
      "537.0"
    ], 
    "514": [
      "136.746", 
      "50202.0", 
      "136.809", 
      "140.073", 
      "11646.0", 
      "140.021", 
      "140.074"
    ], 
    "515": [
      "10802.0", 
      "11634.24", 
      "10826.0"
    ], 
    "516": [
      "136.775", 
      "136.798", 
      "11634.0", 
      "10002.0"
    ], 
    "517": [
      "136.797"
    ], 
    "518": [
      "10842.0", 
      "4.44", 
      "140.063"
    ], 
    "519": [
      "136.774", 
      "302.0", 
      "136.814", 
      "148.0", 
      "140.56"
    ], 
    "520": [
      "250205.0"
    ], 
    "521": [
      "136.805"
    ], 
    "522": [
      "10071.0", 
      "136.773"
    ], 
    "524": [
      "10004.0", 
      "250206.0", 
      "1331.0"
    ], 
    "525": [
      "136.812", 
      "11605.0", 
      "25202.1"
    ], 
    "526": [
      "136.86"
    ], 
    "527": [
      "136.789"
    ], 
    "528": [
      "1330.0", 
      "136.75"
    ], 
    "529": [
      "140.075"
    ], 
    "530": [
      "280.0"
    ], 
    "531": [
      "136.804"
    ], 
    "532": [
      "136.853"
    ], 
    "533": [
      "136.844"
    ], 
    "534": [
      "136.8"
    ], 
    "535": [
      "2500.332", 
      "250200.0"
    ], 
    "536": [
      "140.011", 
      "107.0"
    ], 
    "537": [
      "10824.8"
    ], 
    "538": [
      "136.856", 
      "136.755"
    ], 
    "539": [
      "136.741"
    ], 
    "540": [
      "140.031"
    ], 
    "541": [
      "136.743"
    ], 
    "542": [
      "136.854", 
      "136.857", 
      "10006.0", 
      "1325.91"
    ], 
    "543": [
      "136.881"
    ], 
    "545": [
      "136.74"
    ], 
    "546": [
      "50200.0", 
      "250202.118"
    ], 
    "547": [
      "136.793", 
      "25203.0", 
      "136.799", 
      "25209.0"
    ], 
    "549": [
      "136.8501"
    ], 
    "551": [
      "10024.0"
    ], 
    "553": [
      "136.795", 
      "140.051", 
      "250205.17"
    ], 
    "555": [
      "4.17", 
      "136.884", 
      "136.808", 
      "136.782", 
      "136.85"
    ], 
    "556": [
      "136.873"
    ], 
    "557": [
      "50206.0", 
      "50204.0", 
      "136.768"
    ], 
    "558": [
      "4.29"
    ], 
    "559": [
      "136.76", 
      "136.781"
    ], 
    "560": [
      "10009.0", 
      "140.101", 
      "1356.0", 
      "140.026"
    ], 
    "561": [
      "1001.2", 
      "25214.0"
    ], 
    "563": [
      "136.747", 
      "136.893"
    ], 
    "564": [
      "136.794", 
      "136.875"
    ], 
    "565": [
      "136.806", 
      "136.78"
    ], 
    "568": [
      "136.874"
    ], 
    "569": [
      "136.851"
    ], 
    "570": [
      "25202.2"
    ], 
    "571": [
      "136.766", 
      "10859.0"
    ], 
    "572": [
      "136.882"
    ], 
    "573": [
      "136.84"
    ], 
    "574": [
      "25200.0", 
      "136.885", 
      "10825.0", 
      "11846.19"
    ], 
    "575": [
      "140.05"
    ], 
    "576": [
      "136.855", 
      "140.048"
    ], 
    "578": [
      "11834.13"
    ], 
    "579": [
      "20900.0"
    ], 
    "580": [
      "25202.15", 
      "25208.0"
    ], 
    "581": [
      "136.818", 
      "141.002"
    ], 
    "583": [
      "11846.0"
    ], 
    "585": [
      "10042.0"
    ], 
    "587": [
      "136.817", 
      "140.044", 
      "136.859", 
      "12434.7", 
      "136.89"
    ], 
    "589": [
      "136.821"
    ], 
    "591": [
      "136.784"
    ], 
    "592": [
      "250204.0", 
      "10824.0"
    ], 
    "593": [
      "136.88"
    ], 
    "594": [
      "136.878"
    ], 
    "595": [
      "136.886", 
      "50208.0", 
      "136.811"
    ], 
    "596": [
      "136.777", 
      "10804.0"
    ], 
    "597": [
      "136.739", 
      "250204.17", 
      "136.822"
    ], 
    "598": [
      "136.895", 
      "136.826"
    ], 
    "599": [
      "136.879", 
      "1370.18"
    ], 
    "600": [
      "11834.19"
    ], 
    "601": [
      "136.887", 
      "136.759", 
      "136.82"
    ], 
    "602": [
      "13992502.0", 
      "136.841", 
      "140.027"
    ], 
    "604": [
      "10809.0", 
      "136.891"
    ], 
    "605": [
      "136.847"
    ], 
    "606": [
      "136.889", 
      "250202.172", 
      "250206.182"
    ], 
    "608": [
      "136.785"
    ], 
    "609": [
      "140.065"
    ], 
    "610": [
      "10225.0"
    ], 
    "611": [
      "25207.0", 
      "140.062"
    ], 
    "613": [
      "141.004", 
      "250200.17", 
      "136.763"
    ], 
    "614": [
      "136.787"
    ], 
    "615": [
      "136.866", 
      "136.877", 
      "1000.0"
    ], 
    "616": [
      "140.069", 
      "10804.31", 
      "159.0"
    ], 
    "617": [
      "140.047", 
      "25215.17", 
      "10805.31"
    ], 
    "619": [
      "140.049", 
      "1361.0"
    ], 
    "621": [
      "136.816", 
      "513.0"
    ], 
    "622": [
      "250203.17"
    ], 
    "623": [
      "250208.17", 
      "136.783"
    ], 
    "624": [
      "136.744", 
      "136.888"
    ], 
    "625": [
      "136.898", 
      "136.751"
    ], 
    "626": [
      "136.8862", 
      "136.863"
    ], 
    "627": [
      "136.872", 
      "25202.0", 
      "136.862"
    ], 
    "628": [
      "140.042"
    ], 
    "629": [
      "250200.182", 
      "10224.15"
    ], 
    "630": [
      "10807.0", 
      "25206.0"
    ], 
    "631": [
      "136.861"
    ], 
    "632": [
      "10026.0", 
      "140.025"
    ], 
    "633": [
      "10805.0", 
      "141.036"
    ], 
    "634": [
      "136.788", 
      "149.0"
    ], 
    "635": [
      "136.852", 
      "141.005", 
      "141.006", 
      "25215.0"
    ], 
    "638": [
      "136.807", 
      "10059.0"
    ], 
    "639": [
      "11634.914", 
      "11650.914"
    ], 
    "643": [
      "140.064", 
      "136.786", 
      "136.837"
    ], 
    "644": [
      "1361.181"
    ], 
    "646": [
      "250202.1", 
      "136.8861"
    ], 
    "647": [
      "250202.183", 
      "140.024"
    ], 
    "648": [
      "141.009"
    ], 
    "650": [
      "11834.99", 
      "141.012", 
      "250206.17"
    ], 
    "651": [
      "13034.0", 
      "10007.0", 
      "136.838"
    ], 
    "652": [
      "140.107"
    ], 
    "654": [
      "140.045", 
      "141.007"
    ], 
    "656": [
      "250202.17"
    ], 
    "657": [
      "250208.18", 
      "140.068"
    ], 
    "658": [
      "136.867", 
      "136.869", 
      "136.896", 
      "136.828"
    ], 
    "660": [
      "140.102"
    ], 
    "661": [
      "136.834"
    ], 
    "662": [
      "12834.0"
    ], 
    "663": [
      "11024.2"
    ], 
    "664": [
      "20834.0"
    ], 
    "665": [
      "136.764"
    ], 
    "666": [
      "136.892"
    ], 
    "669": [
      "1360.0", 
      "136.883"
    ], 
    "670": [
      "136.819"
    ], 
    "671": [
      "140.103"
    ], 
    "672": [
      "140.108", 
      "136.876"
    ], 
    "673": [
      "140.067"
    ], 
    "674": [
      "136.833"
    ], 
    "675": [
      "11024.0"
    ], 
    "679": [
      "136.823"
    ], 
    "681": [
      "1361.18"
    ], 
    "682": [
      "141.109"
    ], 
    "683": [
      "11024.6"
    ], 
    "684": [
      "140.046"
    ], 
    "685": [
      "25205.0"
    ], 
    "686": [
      "250202.171"
    ], 
    "687": [
      "141.101"
    ], 
    "688": [
      "158.0"
    ], 
    "689": [
      "250207.18", 
      "141.032"
    ], 
    "690": [
      "10871.0"
    ], 
    "692": [
      "2500.31", 
      "136.761", 
      "140.112", 
      "4.28"
    ], 
    "693": [
      "159.02"
    ], 
    "696": [
      "136.83"
    ], 
    "697": [
      "136.842"
    ], 
    "698": [
      "11834.0"
    ], 
    "701": [
      "139.005"
    ], 
    "702": [
      "10224.0", 
      "250202.2"
    ], 
    "703": [
      "136.8642"
    ], 
    "708": [
      "140.111"
    ], 
    "709": [
      "250202.182"
    ], 
    "710": [
      "12434.0"
    ], 
    "711": [
      "140.11"
    ], 
    "712": [
      "136.865"
    ], 
    "713": [
      "2500.312", 
      "140.105"
    ], 
    "716": [
      "25215.18", 
      "2500.331", 
      "25210.0"
    ], 
    "718": [
      "250203.18"
    ], 
    "719": [
      "250200.18"
    ], 
    "720": [
      "1363.17", 
      "136.835"
    ], 
    "721": [
      "11024.15"
    ], 
    "724": [
      "136.848"
    ], 
    "727": [
      "140.106", 
      "136.829"
    ], 
    "728": [
      "20896.0"
    ], 
    "729": [
      "136.868"
    ], 
    "731": [
      "250202.5"
    ], 
    "732": [
      "136.864"
    ], 
    "737": [
      "250202.4"
    ], 
    "740": [
      "25211.0", 
      "1362.0"
    ], 
    "741": [
      "136.836"
    ], 
    "742": [
      "136.831"
    ], 
    "743": [
      "136.824"
    ], 
    "747": [
      "1362.17"
    ], 
    "748": [
      "136.871"
    ], 
    "751": [
      "1361.17"
    ], 
    "752": [
      "2500.401"
    ], 
    "753": [
      "140.066"
    ], 
    "756": [
      "141.105"
    ], 
    "758": [
      "250205.18"
    ], 
    "759": [
      "11025.0"
    ], 
    "764": [
      "250207.17"
    ], 
    "765": [
      "13034.99"
    ], 
    "766": [
      "2500.311"
    ], 
    "770": [
      "250202.3"
    ], 
    "771": [
      "136.8391"
    ], 
    "777": [
      "1363.18", 
      "1362.18"
    ], 
    "780": [
      "25212.17"
    ], 
    "783": [
      "250206.18"
    ], 
    "785": [
      "11634.911", 
      "12634.0"
    ], 
    "787": [
      "22834.0"
    ], 
    "790": [
      "141.042"
    ], 
    "793": [
      "136.843"
    ], 
    "797": [
      "250202.18"
    ], 
    "798": [
      "25211.18"
    ], 
    "799": [
      "141.037"
    ], 
    "802": [
      "1363.0"
    ], 
    "811": [
      "11650.911"
    ], 
    "815": [
      "250206.181", 
      "141.01"
    ], 
    "816": [
      "25213.0"
    ], 
    "822": [
      "20834.75"
    ], 
    "824": [
      "140.104"
    ], 
    "825": [
      "25213.17"
    ], 
    "826": [
      "136.762", 
      "21034.21", 
      "136.832"
    ], 
    "828": [
      "2500.511"
    ], 
    "837": [
      "141.013"
    ], 
    "838": [
      "250204.18"
    ], 
    "839": [
      "25211.17"
    ], 
    "841": [
      "250202.181"
    ], 
    "845": [
      "25212.18"
    ], 
    "849": [
      "141.011"
    ], 
    "850": [
      "250202.184"
    ], 
    "856": [
      "141.033"
    ], 
    "857": [
      "141.008"
    ], 
    "863": [
      "141.107"
    ], 
    "866": [
      "141.038"
    ], 
    "868": [
      "141.001"
    ], 
    "878": [
      "141.003"
    ], 
    "888": [
      "141.112", 
      "141.031"
    ], 
    "899": [
      "25234.0"
    ], 
    "902": [
      "141.108"
    ], 
    "904": [
      "24034.0"
    ], 
    "907": [
      "12634.99"
    ], 
    "909": [
      "141.039"
    ], 
    "911": [
      "141.035"
    ], 
    "913": [
      "22434.0"
    ], 
    "914": [
      "20834.9", 
      "25212.0"
    ], 
    "916": [
      "21034.999"
    ], 
    "917": [
      "141.102"
    ], 
    "921": [
      "141.049"
    ], 
    "924": [
      "24434.0"
    ], 
    "925": [
      "20834.103"
    ], 
    "926": [
      "141.114"
    ], 
    "929": [
      "2500.601"
    ], 
    "931": [
      "141.111"
    ], 
    "932": [
      "20034.0"
    ], 
    "947": [
      "141.106"
    ], 
    "958": [
      "140.55"
    ], 
    "964": [
      "23634.0"
    ], 
    "967": [
      "25213.18"
    ], 
    "982": [
      "22034.0"
    ], 
    "985": [
      "141.046"
    ], 
    "991": [
      "24834.0", 
      "23234.0"
    ], 
    "992": [
      "511.0"
    ], 
    "996": [
      "158.5"
    ], 
    "1000": [
      "21034.9921", 
      "141.047", 
      "141.103"
    ], 
    "1003": [
      "141.034"
    ], 
    "1008": [
      "141.044"
    ], 
    "1018": [
      "141.048"
    ], 
    "1025": [
      "141.11"
    ], 
    "1028": [
      "141.104"
    ], 
    "1048": [
      "20834.76"
    ], 
    "1049": [
      "141.043"
    ], 
    "1145": [
      "141.041"
    ], 
    "1215": [
      "141.045"
    ], 
    "1219": [
      "137.8"
    ], 
    "1301": [
      "136.9"
    ], 
    "1343": [
      "21034.99"
    ], 
    "1350": [
      "21034.114"
    ], 
    "1595": [
      "138.3"
    ], 
    "1626": [
      "20834.911"
    ], 
    "2445": [
      "159.03"
    ], 
    "3138": [
      "521.0"
    ], 
    "3177": [
      "528.0"
    ], 
    "3188": [
      "516.0"
    ], 
    "3199": [
      "519.0"
    ], 
    "3307": [
      "538.0"
    ], 
    "3315": [
      "512.0"
    ], 
    "3333": [
      "529.0"
    ], 
    "3369": [
      "515.0"
    ], 
    "3372": [
      "547.0"
    ], 
    "3376": [
      "518.0"
    ], 
    "3501": [
      "525.0"
    ], 
    "3543": [
      "526.0"
    ]
  }, 
  "workflows": {
    "1.0": [
      339
    ], 
    "10.0": [
      352
    ], 
    "1000.0": [
      615
    ], 
    "10001.0": [
      459
    ], 
    "10002.0": [
      516
    ], 
    "10003.0": [
      513
    ], 
    "10004.0": [
      524
    ], 
    "10005.0": [
      503
    ], 
    "10006.0": [
      542
    ], 
    "10007.0": [
      651
    ], 
    "10008.0": [
      466
    ], 
    "10009.0": [
      560
    ], 
    "1001.0": [
      501
    ], 
    "1001.2": [
      561
    ], 
    "1001.3": [
      462
    ], 
    "1002.0": [
      345
    ], 
    "1002.3": [
      385
    ], 
    "1002.4": [
      418
    ], 
    "10023.0": [
      484
    ], 
    "10024.0": [
      551
    ], 
    "10024.1": [
      220
    ], 
    "10024.2": [
      366
    ], 
    "10024.3": [
      234
    ], 
    "10024.4": [
      322
    ], 
    "10024.5": [
      201
    ], 
    "10025.0": [
      502
    ], 
    "10026.0": [
      632
    ], 
    "1003.0": [
      303
    ], 
    "1004.0": [
      348
    ], 
    "10042.0": [
      585
    ], 
    "1005.0": [
      141
    ], 
    "10059.0": [
      638
    ], 
    "10071.0": [
      522
    ], 
    "101.0": [
      110
    ], 
    "1010.0": [
      118
    ], 
    "102.0": [
      104
    ], 
    "1020.0": [
      163
    ], 
    "10224.0": [
      702
    ], 
    "10224.15": [
      629
    ], 
    "10225.0": [
      610
    ], 
    "103.0": [
      425
    ], 
    "1030.0": [
      244
    ], 
    "1040.0": [
      371
    ], 
    "1040.1": [
      143
    ], 
    "1041.0": [
      133
    ], 
    "1042.0": [
      297
    ], 
    "10424.0": [
      427
    ], 
    "1043.0": [
      121
    ], 
    "1044.0": [
      134
    ], 
    "1045.0": [
      123
    ], 
    "105.0": [
      192
    ], 
    "1052.0": [
      155
    ], 
    "1052.1": [
      71
    ], 
    "106.0": [
      377
    ], 
    "107.0": [
      536
    ], 
    "108.0": [
      447
    ], 
    "10801.0": [
      490
    ], 
    "10802.0": [
      515
    ], 
    "10803.0": [
      472
    ], 
    "10804.0": [
      596
    ], 
    "10804.31": [
      616
    ], 
    "10805.0": [
      633
    ], 
    "10805.31": [
      617
    ], 
    "10806.0": [
      475
    ], 
    "10807.0": [
      630
    ], 
    "10808.0": [
      493
    ], 
    "10809.0": [
      604
    ], 
    "10823.0": [
      488
    ], 
    "10824.0": [
      592
    ], 
    "10824.1": [
      237
    ], 
    "10824.5": [
      214
    ], 
    "10824.501": [
      198
    ], 
    "10824.505": [
      242
    ], 
    "10824.511": [
      161
    ], 
    "10824.521": [
      167
    ], 
    "10824.6": [
      488
    ], 
    "10824.8": [
      537
    ], 
    "10825.0": [
      574
    ], 
    "10826.0": [
      515
    ], 
    "10842.0": [
      518
    ], 
    "10842.501": [
      213
    ], 
    "10842.505": [
      214
    ], 
    "10859.0": [
      571
    ], 
    "10871.0": [
      690
    ], 
    "109.0": [
      343
    ], 
    "11.0": [
      348
    ], 
    "110.0": [
      379
    ], 
    "1102.0": [
      446
    ], 
    "11024.0": [
      675
    ], 
    "11024.15": [
      721
    ], 
    "11024.2": [
      663
    ], 
    "11024.6": [
      683
    ], 
    "11025.0": [
      759
    ], 
    "111.0": [
      421
    ], 
    "112.0": [
      438
    ], 
    "11224.0": [
      500
    ], 
    "11224.6": [
      437
    ], 
    "113.0": [
      365
    ], 
    "114.0": [
      379
    ], 
    "115.0": [
      368
    ], 
    "116.0": [
      374
    ], 
    "11601.0": [
      423
    ], 
    "11602.0": [
      480
    ], 
    "11603.0": [
      471
    ], 
    "11604.0": [
      510
    ], 
    "11605.0": [
      525
    ], 
    "11606.0": [
      421
    ], 
    "11607.0": [
      511
    ], 
    "11608.0": [
      437
    ], 
    "11609.0": [
      492
    ], 
    "11630.0": [
      468
    ], 
    "11634.0": [
      516
    ], 
    "11634.1": [
      288
    ], 
    "11634.15": [
      469
    ], 
    "11634.24": [
      515
    ], 
    "11634.5": [
      186
    ], 
    "11634.501": [
      206
    ], 
    "11634.505": [
      226
    ], 
    "11634.511": [
      162
    ], 
    "11634.521": [
      167
    ], 
    "11634.601": [
      434
    ], 
    "11634.7": [
      445
    ], 
    "11634.91": [
      444
    ], 
    "11634.911": [
      785
    ], 
    "11634.914": [
      639
    ], 
    "11640.0": [
      426
    ], 
    "11643.0": [
      476
    ], 
    "11646.0": [
      514
    ], 
    "11650.0": [
      426
    ], 
    "11650.501": [
      239
    ], 
    "11650.505": [
      197
    ], 
    "11650.911": [
      811
    ], 
    "11650.914": [
      639
    ], 
    "117.0": [
      350
    ], 
    "11723.17": [
      478
    ], 
    "118.0": [
      378
    ], 
    "11834.0": [
      698
    ], 
    "11834.13": [
      578
    ], 
    "11834.19": [
      600
    ], 
    "11834.21": [
      358
    ], 
    "11834.24": [
      392
    ], 
    "11834.99": [
      650
    ], 
    "11846.0": [
      583
    ], 
    "11846.19": [
      574
    ], 
    "119.0": [
      387
    ], 
    "12.0": [
      378
    ], 
    "120.0": [
      442
    ], 
    "12034.0": [
      387
    ], 
    "121.0": [
      361
    ], 
    "122.0": [
      344
    ], 
    "123.1": [
      119
    ], 
    "123.2": [
      111
    ], 
    "123.3": [
      113
    ], 
    "124.1": [
      119
    ], 
    "124.2": [
      142
    ], 
    "124.4": [
      126
    ], 
    "124.5": [
      90
    ], 
    "124.6": [
      145
    ], 
    "12434.0": [
      710
    ], 
    "12434.7": [
      587
    ], 
    "125.0": [
      390
    ], 
    "126.0": [
      418
    ], 
    "12634.0": [
      785
    ], 
    "12634.99": [
      907
    ], 
    "127.0": [
      377
    ], 
    "128.0": [
      393
    ], 
    "12834.0": [
      662
    ], 
    "129.0": [
      384
    ], 
    "13.0": [
      430
    ], 
    "130.0": [
      375
    ], 
    "1301.0": [
      335
    ], 
    "1301.17": [
      275
    ], 
    "1302.0": [
      254
    ], 
    "1302.17": [
      312
    ], 
    "1302.18": [
      374
    ], 
    "1302.181": [
      359
    ], 
    "1303.0": [
      363
    ], 
    "1303.17": [
      396
    ], 
    "13034.0": [
      651
    ], 
    "13034.99": [
      765
    ], 
    "1304.18": [
      335
    ], 
    "1304.181": [
      333
    ], 
    "1304.182": [
      306
    ], 
    "1306.0": [
      375
    ], 
    "1307.0": [
      220
    ], 
    "1308.0": [
      287
    ], 
    "1309.0": [
      404
    ], 
    "131.0": [
      388
    ], 
    "1310.0": [
      379
    ], 
    "1311.0": [
      374
    ], 
    "1312.0": [
      419
    ], 
    "1313.0": [
      378
    ], 
    "1314.0": [
      364
    ], 
    "1315.0": [
      373
    ], 
    "1316.0": [
      410
    ], 
    "1317.0": [
      484
    ], 
    "1318.0": [
      493
    ], 
    "1319.0": [
      378
    ], 
    "132.0": [
      364
    ], 
    "1320.0": [
      449
    ], 
    "1321.0": [
      462
    ], 
    "1322.0": [
      502
    ], 
    "1323.0": [
      450
    ], 
    "13234.0": [
      314
    ], 
    "1324.0": [
      435
    ], 
    "13240.303": [
      150
    ], 
    "1325.0": [
      498
    ], 
    "1325.1": [
      293
    ], 
    "1325.2": [
      350
    ], 
    "1325.3": [
      224
    ], 
    "1325.4": [
      374
    ], 
    "1325.5": [
      329
    ], 
    "1325.51": [
      267
    ], 
    "1325.516": [
      268
    ], 
    "1325.5161": [
      231
    ], 
    "1325.517": [
      268
    ], 
    "1325.518": [
      236
    ], 
    "1325.9": [
      495
    ], 
    "1325.91": [
      542
    ], 
    "1326.0": [
      383
    ], 
    "1327.0": [
      389
    ], 
    "1328.0": [
      365
    ], 
    "1329.0": [
      464
    ], 
    "133.0": [
      424
    ], 
    "1330.0": [
      528
    ], 
    "1331.0": [
      524
    ], 
    "1332.0": [
      425
    ], 
    "1333.0": [
      427
    ], 
    "1334.0": [
      368
    ], 
    "1335.0": [
      394
    ], 
    "1336.0": [
      471
    ], 
    "1337.0": [
      438
    ], 
    "1338.0": [
      492
    ], 
    "1339.0": [
      423
    ], 
    "134.0": [
      386
    ], 
    "134.701": [
      482
    ], 
    "134.702": [
      389
    ], 
    "134.703": [
      350
    ], 
    "134.704": [
      382
    ], 
    "134.705": [
      356
    ], 
    "134.706": [
      390
    ], 
    "134.707": [
      338
    ], 
    "134.708": [
      342
    ], 
    "134.709": [
      371
    ], 
    "134.71": [
      453
    ], 
    "134.801": [
      469
    ], 
    "134.802": [
      365
    ], 
    "134.803": [
      361
    ], 
    "134.804": [
      387
    ], 
    "134.805": [
      395
    ], 
    "134.806": [
      392
    ], 
    "134.807": [
      480
    ], 
    "134.808": [
      454
    ], 
    "134.809": [
      367
    ], 
    "134.81": [
      402
    ], 
    "134.811": [
      388
    ], 
    "134.812": [
      460
    ], 
    "134.813": [
      219
    ], 
    "134.901": [
      481
    ], 
    "134.902": [
      353
    ], 
    "134.903": [
      324
    ], 
    "134.904": [
      362
    ], 
    "134.905": [
      375
    ], 
    "134.906": [
      348
    ], 
    "134.907": [
      439
    ], 
    "134.908": [
      383
    ], 
    "134.909": [
      332
    ], 
    "134.91": [
      335
    ], 
    "134.911": [
      336
    ], 
    "134.912": [
      457
    ], 
    "134.99601": [
      392
    ], 
    "134.99602": [
      468
    ], 
    "134.99603": [
      374
    ], 
    "134.99901": [
      320
    ], 
    "1340.0": [
      432
    ], 
    "1341.0": [
      487
    ], 
    "1343.0": [
      378
    ], 
    "13434.0": [
      442
    ], 
    "1344.0": [
      367
    ], 
    "1345.0": [
      422
    ], 
    "1347.0": [
      431
    ], 
    "1348.0": [
      391
    ], 
    "1349.0": [
      383
    ], 
    "135.1": [
      371
    ], 
    "135.11": [
      418
    ], 
    "135.12": [
      343
    ], 
    "135.13": [
      201
    ], 
    "135.14": [
      371
    ], 
    "135.2": [
      356
    ], 
    "135.3": [
      365
    ], 
    "135.4": [
      407
    ], 
    "135.5": [
      408
    ], 
    "135.6": [
      390
    ], 
    "135.7": [
      307
    ], 
    "135.8": [
      61
    ], 
    "135.9": [
      403
    ], 
    "1350.0": [
      413
    ], 
    "1351.0": [
      369
    ], 
    "1352.0": [
      415
    ], 
    "1353.0": [
      355
    ], 
    "1354.0": [
      429
    ], 
    "1355.0": [
      440
    ], 
    "1356.0": [
      560
    ], 
    "136.721": [
      422
    ], 
    "136.722": [
      423
    ], 
    "136.723": [
      395
    ], 
    "136.724": [
      445
    ], 
    "136.72411": [
      294
    ], 
    "136.72412": [
      345
    ], 
    "136.725": [
      508
    ], 
    "136.726": [
      446
    ], 
    "136.727": [
      472
    ], 
    "136.728": [
      500
    ], 
    "136.729": [
      386
    ], 
    "136.73": [
      433
    ], 
    "136.731": [
      428
    ], 
    "136.732": [
      407
    ], 
    "136.733": [
      181
    ], 
    "136.734": [
      433
    ], 
    "136.735": [
      454
    ], 
    "136.736": [
      461
    ], 
    "136.737": [
      513
    ], 
    "136.738": [
      492
    ], 
    "136.739": [
      597
    ], 
    "136.74": [
      545
    ], 
    "136.741": [
      539
    ], 
    "136.742": [
      460
    ], 
    "136.743": [
      541
    ], 
    "136.744": [
      624
    ], 
    "136.745": [
      431
    ], 
    "136.746": [
      514
    ], 
    "136.747": [
      563
    ], 
    "136.748": [
      506
    ], 
    "136.749": [
      498
    ], 
    "136.75": [
      528
    ], 
    "136.751": [
      625
    ], 
    "136.752": [
      508
    ], 
    "136.753": [
      476
    ], 
    "136.754": [
      467
    ], 
    "136.755": [
      538
    ], 
    "136.756": [
      428
    ], 
    "136.757": [
      489
    ], 
    "136.758": [
      504
    ], 
    "136.759": [
      601
    ], 
    "136.76": [
      559
    ], 
    "136.761": [
      692
    ], 
    "136.7611": [
      247
    ], 
    "136.76111": [
      305
    ], 
    "136.762": [
      826
    ], 
    "136.763": [
      613
    ], 
    "136.764": [
      665
    ], 
    "136.765": [
      505
    ], 
    "136.766": [
      571
    ], 
    "136.767": [
      494
    ], 
    "136.768": [
      557
    ], 
    "136.769": [
      475
    ], 
    "136.77": [
      495
    ], 
    "136.771": [
      481
    ], 
    "136.772": [
      507
    ], 
    "136.7721": [
      292
    ], 
    "136.77211": [
      249
    ], 
    "136.773": [
      522
    ], 
    "136.774": [
      519
    ], 
    "136.775": [
      516
    ], 
    "136.776": [
      446
    ], 
    "136.777": [
      596
    ], 
    "136.778": [
      404
    ], 
    "136.779": [
      494
    ], 
    "136.78": [
      565
    ], 
    "136.7801": [
      139
    ], 
    "136.7802": [
      114
    ], 
    "136.7803": [
      187
    ], 
    "136.781": [
      559
    ], 
    "136.782": [
      555
    ], 
    "136.783": [
      623
    ], 
    "136.784": [
      591
    ], 
    "136.785": [
      608
    ], 
    "136.786": [
      643
    ], 
    "136.787": [
      614
    ], 
    "136.788": [
      634
    ], 
    "136.789": [
      527
    ], 
    "136.79": [
      454
    ], 
    "136.791": [
      430
    ], 
    "136.792": [
      491
    ], 
    "136.793": [
      547
    ], 
    "136.794": [
      564
    ], 
    "136.795": [
      553
    ], 
    "136.796": [
      507
    ], 
    "136.797": [
      517
    ], 
    "136.798": [
      516
    ], 
    "136.799": [
      547
    ], 
    "136.8": [
      534
    ], 
    "136.801": [
      450
    ], 
    "136.802": [
      500
    ], 
    "136.803": [
      474
    ], 
    "136.804": [
      531
    ], 
    "136.805": [
      521
    ], 
    "136.806": [
      565
    ], 
    "136.807": [
      638
    ], 
    "136.808": [
      555
    ], 
    "136.809": [
      514
    ], 
    "136.81": [
      497
    ], 
    "136.811": [
      595
    ], 
    "136.812": [
      525
    ], 
    "136.813": [
      441
    ], 
    "136.814": [
      519
    ], 
    "136.815": [
      504
    ], 
    "136.816": [
      621
    ], 
    "136.817": [
      587
    ], 
    "136.818": [
      581
    ], 
    "136.819": [
      670
    ], 
    "136.82": [
      601
    ], 
    "136.821": [
      589
    ], 
    "136.822": [
      597
    ], 
    "136.823": [
      679
    ], 
    "136.824": [
      743
    ], 
    "136.825": [
      497
    ], 
    "136.826": [
      598
    ], 
    "136.827": [
      481
    ], 
    "136.828": [
      658
    ], 
    "136.829": [
      727
    ], 
    "136.83": [
      696
    ], 
    "136.831": [
      742
    ], 
    "136.8311": [
      249
    ], 
    "136.83111": [
      292
    ], 
    "136.832": [
      826
    ], 
    "136.833": [
      674
    ], 
    "136.834": [
      661
    ], 
    "136.835": [
      720
    ], 
    "136.836": [
      741
    ], 
    "136.837": [
      643
    ], 
    "136.838": [
      651
    ], 
    "136.839": [
      466
    ], 
    "136.8391": [
      771
    ], 
    "136.84": [
      573
    ], 
    "136.841": [
      602
    ], 
    "136.842": [
      697
    ], 
    "136.843": [
      793
    ], 
    "136.844": [
      533
    ], 
    "136.845": [
      496
    ], 
    "136.846": [
      473
    ], 
    "136.847": [
      605
    ], 
    "136.848": [
      724
    ], 
    "136.849": [
      498
    ], 
    "136.85": [
      555
    ], 
    "136.8501": [
      549
    ], 
    "136.851": [
      569
    ], 
    "136.852": [
      635
    ], 
    "136.853": [
      532
    ], 
    "136.854": [
      542
    ], 
    "136.855": [
      576
    ], 
    "136.856": [
      538
    ], 
    "136.8561": [
      455
    ], 
    "136.8562": [
      422
    ], 
    "136.857": [
      542
    ], 
    "136.858": [
      501
    ], 
    "136.859": [
      587
    ], 
    "136.86": [
      526
    ], 
    "136.861": [
      631
    ], 
    "136.862": [
      627
    ], 
    "136.863": [
      626
    ], 
    "136.864": [
      732
    ], 
    "136.8642": [
      703
    ], 
    "136.865": [
      712
    ], 
    "136.866": [
      615
    ], 
    "136.867": [
      658
    ], 
    "136.868": [
      729
    ], 
    "136.869": [
      658
    ], 
    "136.87": [
      504
    ], 
    "136.871": [
      748
    ], 
    "136.872": [
      627
    ], 
    "136.873": [
      556
    ], 
    "136.874": [
      568
    ], 
    "136.875": [
      564
    ], 
    "136.876": [
      672
    ], 
    "136.877": [
      615
    ], 
    "136.878": [
      594
    ], 
    "136.879": [
      599
    ], 
    "136.88": [
      593
    ], 
    "136.881": [
      543
    ], 
    "136.882": [
      572
    ], 
    "136.883": [
      669
    ], 
    "136.884": [
      555
    ], 
    "136.885": [
      574
    ], 
    "136.8855": [
      161
    ], 
    "136.885501": [
      176
    ], 
    "136.885511": [
      184
    ], 
    "136.885521": [
      172
    ], 
    "136.886": [
      595
    ], 
    "136.8861": [
      646
    ], 
    "136.8862": [
      626
    ], 
    "136.887": [
      601
    ], 
    "136.888": [
      624
    ], 
    "136.88811": [
      291
    ], 
    "136.8885": [
      153
    ], 
    "136.888501": [
      197
    ], 
    "136.888511": [
      180
    ], 
    "136.888521": [
      147
    ], 
    "136.889": [
      606
    ], 
    "136.89": [
      587
    ], 
    "136.891": [
      604
    ], 
    "136.892": [
      666
    ], 
    "136.893": [
      563
    ], 
    "136.894": [
      448
    ], 
    "136.895": [
      598
    ], 
    "136.896": [
      658
    ], 
    "136.897": [
      208
    ], 
    "136.898": [
      625
    ], 
    "136.899": [
      171
    ], 
    "136.9": [
      1301
    ], 
    "1360.0": [
      669
    ], 
    "1361.0": [
      619
    ], 
    "1361.17": [
      751
    ], 
    "1361.18": [
      681
    ], 
    "1361.181": [
      644
    ], 
    "1362.0": [
      740
    ], 
    "1362.17": [
      747
    ], 
    "1362.18": [
      777
    ], 
    "1363.0": [
      802
    ], 
    "1363.17": [
      720
    ], 
    "1363.18": [
      777
    ], 
    "1364.0": [
      425
    ], 
    "1365.0": [
      416
    ], 
    "1366.0": [
      445
    ], 
    "137.8": [
      1219
    ], 
    "1370.0": [
      512
    ], 
    "1370.17": [
      481
    ], 
    "1370.18": [
      599
    ], 
    "138.1": [
      203
    ], 
    "138.2": [
      150
    ], 
    "138.3": [
      1595
    ], 
    "138.4": [
      198
    ], 
    "138.5": [
      315
    ], 
    "139.001": [
      417
    ], 
    "139.002": [
      442
    ], 
    "139.003": [
      386
    ], 
    "139.004": [
      507
    ], 
    "139.005": [
      701
    ], 
    "139901.0": [
      358
    ], 
    "139902.0": [
      395
    ], 
    "13992501.0": [
      497
    ], 
    "13992502.0": [
      602
    ], 
    "14.0": [
      373
    ], 
    "140.0": [
      381
    ], 
    "140.001": [
      447
    ], 
    "140.002": [
      407
    ], 
    "140.003": [
      420
    ], 
    "140.004": [
      418
    ], 
    "140.005": [
      377
    ], 
    "140.006": [
      441
    ], 
    "140.007": [
      457
    ], 
    "140.008": [
      468
    ], 
    "140.009": [
      416
    ], 
    "140.01": [
      428
    ], 
    "140.011": [
      536
    ], 
    "140.021": [
      514
    ], 
    "140.022": [
      463
    ], 
    "140.023": [
      427
    ], 
    "140.024": [
      647
    ], 
    "140.025": [
      632
    ], 
    "140.026": [
      560
    ], 
    "140.027": [
      602
    ], 
    "140.028": [
      504
    ], 
    "140.029": [
      488
    ], 
    "140.03": [
      473
    ], 
    "140.031": [
      540
    ], 
    "140.042": [
      628
    ], 
    "140.043": [
      455
    ], 
    "140.044": [
      587
    ], 
    "140.045": [
      654
    ], 
    "140.046": [
      684
    ], 
    "140.047": [
      617
    ], 
    "140.048": [
      576
    ], 
    "140.049": [
      619
    ], 
    "140.05": [
      575
    ], 
    "140.051": [
      553
    ], 
    "140.062": [
      611
    ], 
    "140.063": [
      518
    ], 
    "140.064": [
      643
    ], 
    "140.065": [
      609
    ], 
    "140.065505": [
      225
    ], 
    "140.065511": [
      161
    ], 
    "140.065521": [
      172
    ], 
    "140.066": [
      753
    ], 
    "140.067": [
      673
    ], 
    "140.068": [
      657
    ], 
    "140.069": [
      616
    ], 
    "140.071": [
      453
    ], 
    "140.072": [
      455
    ], 
    "140.073": [
      514
    ], 
    "140.074": [
      514
    ], 
    "140.075": [
      529
    ], 
    "140.076": [
      483
    ], 
    "140.077": [
      465
    ], 
    "140.078": [
      483
    ], 
    "140.101": [
      560
    ], 
    "140.102": [
      660
    ], 
    "140.103": [
      671
    ], 
    "140.104": [
      824
    ], 
    "140.105": [
      713
    ], 
    "140.106": [
      727
    ], 
    "140.107": [
      652
    ], 
    "140.108": [
      672
    ], 
    "140.109": [
      450
    ], 
    "140.11": [
      711
    ], 
    "140.111": [
      708
    ], 
    "140.112": [
      692
    ], 
    "140.113": [
      357
    ], 
    "140.201": [
      122
    ], 
    "140.202": [
      200
    ], 
    "140.51": [
      291
    ], 
    "140.52": [
      336
    ], 
    "140.53": [
      182
    ], 
    "140.54": [
      287
    ], 
    "140.55": [
      958
    ], 
    "140.56": [
      519
    ], 
    "140.5611": [
      225
    ], 
    "140.57": [
      261
    ], 
    "140.58": [
      418
    ], 
    "140.6": [
      211
    ], 
    "140.61": [
      231
    ], 
    "14034.0": [
      341
    ], 
    "14040.303": [
      186
    ], 
    "141.001": [
      868
    ], 
    "141.002": [
      581
    ], 
    "141.003": [
      878
    ], 
    "141.004": [
      613
    ], 
    "141.005": [
      635
    ], 
    "141.006": [
      635
    ], 
    "141.007": [
      654
    ], 
    "141.008": [
      857
    ], 
    "141.009": [
      648
    ], 
    "141.01": [
      815
    ], 
    "141.011": [
      849
    ], 
    "141.012": [
      650
    ], 
    "141.013": [
      837
    ], 
    "141.031": [
      888
    ], 
    "141.032": [
      689
    ], 
    "141.033": [
      856
    ], 
    "141.034": [
      1003
    ], 
    "141.035": [
      911
    ], 
    "141.036": [
      633
    ], 
    "141.037": [
      799
    ], 
    "141.038": [
      866
    ], 
    "141.039": [
      909
    ], 
    "141.041": [
      1145
    ], 
    "141.042": [
      790
    ], 
    "141.043": [
      1049
    ], 
    "141.044": [
      1008
    ], 
    "141.045": [
      1215
    ], 
    "141.046": [
      985
    ], 
    "141.047": [
      1000
    ], 
    "141.048": [
      1018
    ], 
    "141.049": [
      921
    ], 
    "141.101": [
      687
    ], 
    "141.102": [
      917
    ], 
    "141.103": [
      1000
    ], 
    "141.104": [
      1028
    ], 
    "141.105": [
      756
    ], 
    "141.106": [
      947
    ], 
    "141.107": [
      863
    ], 
    "141.108": [
      902
    ], 
    "141.109": [
      682
    ], 
    "141.11": [
      1025
    ], 
    "141.111": [
      931
    ], 
    "141.112": [
      888
    ], 
    "141.113": [
      340
    ], 
    "141.114": [
      926
    ], 
    "14234.0": [
      441
    ], 
    "144.6": [
      336
    ], 
    "145.0": [
      405
    ], 
    "148.0": [
      519
    ], 
    "149.0": [
      634
    ], 
    "15.0": [
      342
    ], 
    "150.0": [
      450
    ], 
    "158.0": [
      688
    ], 
    "158.01": [
      243
    ], 
    "158.1": [
      387
    ], 
    "158.2": [
      377
    ], 
    "158.3": [
      423
    ], 
    "158.5": [
      996
    ], 
    "159.0": [
      616
    ], 
    "159.01": [
      235
    ], 
    "159.02": [
      693
    ], 
    "159.03": [
      2445
    ], 
    "159.1": [
      407
    ], 
    "159.2": [
      396
    ], 
    "159.3": [
      447
    ], 
    "159.4": [
      450
    ], 
    "16.0": [
      333
    ], 
    "17.0": [
      310
    ], 
    "18.0": [
      301
    ], 
    "19.0": [
      295
    ], 
    "2.0": [
      308
    ], 
    "20.0": [
      306
    ], 
    "200.0": [
      442
    ], 
    "20034.0": [
      932
    ], 
    "2017.1": [
      398
    ], 
    "2017.11": [
      431
    ], 
    "2017.12": [
      336
    ], 
    "2017.13": [
      218
    ], 
    "2017.2": [
      394
    ], 
    "2017.3": [
      349
    ], 
    "2017.4": [
      362
    ], 
    "2017.5": [
      313
    ], 
    "2017.6": [
      356
    ], 
    "2017.7": [
      362
    ], 
    "2017.8": [
      78
    ], 
    "2017.9": [
      332
    ], 
    "2018.1": [
      383
    ], 
    "2018.11": [
      363
    ], 
    "2018.12": [
      337
    ], 
    "2018.13": [
      221
    ], 
    "2018.2": [
      310
    ], 
    "2018.3": [
      354
    ], 
    "2018.4": [
      406
    ], 
    "2018.5": [
      429
    ], 
    "2018.6": [
      420
    ], 
    "2018.7": [
      334
    ], 
    "2018.8": [
      73
    ], 
    "2018.9": [
      365
    ], 
    "202.0": [
      476
    ], 
    "203.0": [
      439
    ], 
    "204.0": [
      461
    ], 
    "205.0": [
      493
    ], 
    "20834.0": [
      664
    ], 
    "20834.103": [
      925
    ], 
    "20834.21": [
      441
    ], 
    "20834.5": [
      444
    ], 
    "20834.501": [
      353
    ], 
    "20834.502": [
      439
    ], 
    "20834.75": [
      822
    ], 
    "20834.76": [
      1048
    ], 
    "20834.9": [
      914
    ], 
    "20834.911": [
      1626
    ], 
    "20896.0": [
      728
    ], 
    "20900.0": [
      579
    ], 
    "21.0": [
      343
    ], 
    "21034.114": [
      1350
    ], 
    "21034.21": [
      826
    ], 
    "21034.99": [
      1343
    ], 
    "21034.9921": [
      1000
    ], 
    "21034.999": [
      916
    ], 
    "21061.97": [
      385
    ], 
    "22.0": [
      328
    ], 
    "22034.0": [
      982
    ], 
    "22434.0": [
      913
    ], 
    "22834.0": [
      787
    ], 
    "23.0": [
      353
    ], 
    "23234.0": [
      991
    ], 
    "23634.0": [
      964
    ], 
    "24.0": [
      352
    ], 
    "24034.0": [
      904
    ], 
    "24434.0": [
      924
    ], 
    "24834.0": [
      991
    ], 
    "25.0": [
      446
    ], 
    "2500.31": [
      692
    ], 
    "2500.311": [
      766
    ], 
    "2500.312": [
      713
    ], 
    "2500.33": [
      400
    ], 
    "2500.331": [
      716
    ], 
    "2500.332": [
      535
    ], 
    "2500.401": [
      752
    ], 
    "2500.501": [
      367
    ], 
    "2500.511": [
      828
    ], 
    "2500.5111": [
      172
    ], 
    "2500.601": [
      929
    ], 
    "250199.0": [
      164
    ], 
    "250199.17": [
      138
    ], 
    "250199.18": [
      162
    ], 
    "250200.0": [
      535
    ], 
    "250200.1": [
      331
    ], 
    "250200.117": [
      368
    ], 
    "250200.118": [
      443
    ], 
    "250200.17": [
      613
    ], 
    "250200.18": [
      719
    ], 
    "250200.182": [
      629
    ], 
    "250202.0": [
      480
    ], 
    "250202.1": [
      646
    ], 
    "250202.118": [
      546
    ], 
    "250202.17": [
      656
    ], 
    "250202.171": [
      686
    ], 
    "250202.172": [
      606
    ], 
    "250202.18": [
      797
    ], 
    "250202.181": [
      841
    ], 
    "250202.182": [
      709
    ], 
    "250202.183": [
      647
    ], 
    "250202.184": [
      850
    ], 
    "250202.2": [
      702
    ], 
    "250202.3": [
      770
    ], 
    "250202.4": [
      737
    ], 
    "250202.5": [
      731
    ], 
    "250203.0": [
      480
    ], 
    "250203.17": [
      622
    ], 
    "250203.18": [
      718
    ], 
    "250204.0": [
      592
    ], 
    "250204.17": [
      597
    ], 
    "250204.18": [
      838
    ], 
    "250205.0": [
      520
    ], 
    "250205.17": [
      553
    ], 
    "250205.18": [
      758
    ], 
    "250206.0": [
      524
    ], 
    "250206.118": [
      453
    ], 
    "250206.17": [
      650
    ], 
    "250206.18": [
      783
    ], 
    "250206.181": [
      815
    ], 
    "250206.182": [
      606
    ], 
    "250207.0": [
      428
    ], 
    "250207.17": [
      764
    ], 
    "250207.18": [
      689
    ], 
    "250208.17": [
      623
    ], 
    "250208.18": [
      657
    ], 
    "250399.0": [
      86
    ], 
    "250399.17": [
      113
    ], 
    "250399.18": [
      111
    ], 
    "250400.0": [
      326
    ], 
    "250400.17": [
      348
    ], 
    "250400.18": [
      304
    ], 
    "250402.0": [
      315
    ], 
    "250402.1": [
      257
    ], 
    "250402.17": [
      333
    ], 
    "250402.171": [
      317
    ], 
    "250402.18": [
      305
    ], 
    "250402.181": [
      297
    ], 
    "250403.0": [
      310
    ], 
    "250403.17": [
      322
    ], 
    "250403.18": [
      343
    ], 
    "250405.0": [
      350
    ], 
    "250405.17": [
      298
    ], 
    "250405.18": [
      402
    ], 
    "250406.0": [
      304
    ], 
    "250406.17": [
      377
    ], 
    "250406.18": [
      390
    ], 
    "250407.0": [
      314
    ], 
    "250407.17": [
      326
    ], 
    "250407.18": [
      330
    ], 
    "250408.0": [
      336
    ], 
    "250408.17": [
      324
    ], 
    "250408.18": [
      308
    ], 
    "250409.0": [
      342
    ], 
    "250409.17": [
      323
    ], 
    "250409.18": [
      365
    ], 
    "25200.0": [
      574
    ], 
    "25202.0": [
      627
    ], 
    "25202.1": [
      525
    ], 
    "25202.15": [
      580
    ], 
    "25202.2": [
      570
    ], 
    "25203.0": [
      547
    ], 
    "25204.0": [
      424
    ], 
    "25205.0": [
      685
    ], 
    "25206.0": [
      630
    ], 
    "25207.0": [
      611
    ], 
    "25208.0": [
      580
    ], 
    "25209.0": [
      547
    ], 
    "25210.0": [
      716
    ], 
    "25211.0": [
      740
    ], 
    "25211.17": [
      839
    ], 
    "25211.18": [
      798
    ], 
    "25212.0": [
      914
    ], 
    "25212.17": [
      780
    ], 
    "25212.18": [
      845
    ], 
    "25213.0": [
      816
    ], 
    "25213.17": [
      825
    ], 
    "25213.18": [
      967
    ], 
    "25214.0": [
      561
    ], 
    "25215.0": [
      635
    ], 
    "25215.17": [
      617
    ], 
    "25215.18": [
      716
    ], 
    "25234.0": [
      899
    ], 
    "25400.0": [
      353
    ], 
    "25400.17": [
      378
    ], 
    "25400.18": [
      311
    ], 
    "25402.0": [
      345
    ], 
    "25402.17": [
      361
    ], 
    "25402.18": [
      368
    ], 
    "25403.0": [
      302
    ], 
    "25403.17": [
      319
    ], 
    "25403.18": [
      338
    ], 
    "25405.0": [
      303
    ], 
    "25405.17": [
      329
    ], 
    "25405.18": [
      344
    ], 
    "25406.0": [
      375
    ], 
    "25406.17": [
      378
    ], 
    "25406.18": [
      340
    ], 
    "25407.0": [
      328
    ], 
    "25407.17": [
      321
    ], 
    "25407.18": [
      317
    ], 
    "25408.0": [
      365
    ], 
    "25408.17": [
      364
    ], 
    "25408.18": [
      346
    ], 
    "25409.0": [
      289
    ], 
    "25409.17": [
      408
    ], 
    "25409.18": [
      346
    ], 
    "26.0": [
      363
    ], 
    "27.0": [
      351
    ], 
    "28.0": [
      393
    ], 
    "280.0": [
      530
    ], 
    "281.0": [
      445
    ], 
    "29.0": [
      363
    ], 
    "3.0": [
      382
    ], 
    "30.0": [
      350
    ], 
    "300.0": [
      459
    ], 
    "301.0": [
      504
    ], 
    "302.0": [
      519
    ], 
    "31.0": [
      349
    ], 
    "310.0": [
      494
    ], 
    "311.0": [
      513
    ], 
    "312.0": [
      452
    ], 
    "32.0": [
      329
    ], 
    "33.0": [
      327
    ], 
    "34.0": [
      480
    ], 
    "35.0": [
      356
    ], 
    "36.0": [
      492
    ], 
    "37.0": [
      367
    ], 
    "38.0": [
      357
    ], 
    "39.0": [
      423
    ], 
    "4.17": [
      555
    ], 
    "4.22": [
      258
    ], 
    "4.23": [
      472
    ], 
    "4.24": [
      402
    ], 
    "4.25": [
      406
    ], 
    "4.26": [
      424
    ], 
    "4.27": [
      449
    ], 
    "4.28": [
      692
    ], 
    "4.29": [
      558
    ], 
    "4.34": [
      443
    ], 
    "4.36": [
      414
    ], 
    "4.37": [
      488
    ], 
    "4.4": [
      429
    ], 
    "4.41": [
      362
    ], 
    "4.42": [
      356
    ], 
    "4.43": [
      461
    ], 
    "4.44": [
      518
    ], 
    "4.45": [
      422
    ], 
    "4.51": [
      394
    ], 
    "4.52": [
      368
    ], 
    "4.53": [
      358
    ], 
    "4.54": [
      373
    ], 
    "4.55": [
      399
    ], 
    "4.57": [
      437
    ], 
    "4.58": [
      493
    ], 
    "4.6": [
      422
    ], 
    "4.61": [
      363
    ], 
    "4.62": [
      379
    ], 
    "4.63": [
      434
    ], 
    "4.64": [
      398
    ], 
    "4.65": [
      448
    ], 
    "4.67": [
      398
    ], 
    "4.68": [
      368
    ], 
    "4.71": [
      422
    ], 
    "4.72": [
      344
    ], 
    "4.73": [
      376
    ], 
    "4.74": [
      352
    ], 
    "4.75": [
      393
    ], 
    "4.76": [
      421
    ], 
    "4.77": [
      418
    ], 
    "4.78": [
      391
    ], 
    "4000.0": [
      307
    ], 
    "4001.0": [
      412
    ], 
    "4002.0": [
      309
    ], 
    "4003.0": [
      277
    ], 
    "4006.0": [
      474
    ], 
    "4007.0": [
      371
    ], 
    "4008.0": [
      481
    ], 
    "43.0": [
      336
    ], 
    "44.0": [
      363
    ], 
    "45.0": [
      391
    ], 
    "5.1": [
      178
    ], 
    "5.2": [
      187
    ], 
    "5.3": [
      195
    ], 
    "5.4": [
      160
    ], 
    "5.5": [
      167
    ], 
    "5.6": [
      197
    ], 
    "5.7": [
      201
    ], 
    "500199.0": [
      122
    ], 
    "500200.0": [
      479
    ], 
    "500200.1": [
      357
    ], 
    "500202.0": [
      478
    ], 
    "500203.0": [
      384
    ], 
    "500204.0": [
      385
    ], 
    "500205.0": [
      426
    ], 
    "500206.0": [
      409
    ], 
    "500207.0": [
      411
    ], 
    "50200.0": [
      546
    ], 
    "50202.0": [
      514
    ], 
    "50203.0": [
      501
    ], 
    "50204.0": [
      557
    ], 
    "50205.0": [
      509
    ], 
    "50206.0": [
      557
    ], 
    "50207.0": [
      440
    ], 
    "50208.0": [
      595
    ], 
    "503.0": [
      179
    ], 
    "504.0": [
      85
    ], 
    "505.0": [
      102
    ], 
    "506.0": [
      70
    ], 
    "507.0": [
      150
    ], 
    "508.0": [
      99
    ], 
    "509.0": [
      85
    ], 
    "510.0": [
      198
    ], 
    "511.0": [
      992
    ], 
    "512.0": [
      3315
    ], 
    "513.0": [
      621
    ], 
    "514.0": [
      129
    ], 
    "515.0": [
      3369
    ], 
    "516.0": [
      3188
    ], 
    "517.0": [
      124
    ], 
    "518.0": [
      3376
    ], 
    "519.0": [
      3199
    ], 
    "520.0": [
      122
    ], 
    "521.0": [
      3138
    ], 
    "522.0": [
      273
    ], 
    "523.0": [
      314
    ], 
    "524.0": [
      121
    ], 
    "525.0": [
      3501
    ], 
    "526.0": [
      3543
    ], 
    "527.0": [
      154
    ], 
    "528.0": [
      3177
    ], 
    "529.0": [
      3333
    ], 
    "530.0": [
      165
    ], 
    "531.0": [
      78
    ], 
    "534.0": [
      266
    ], 
    "535.0": [
      144
    ], 
    "536.0": [
      125
    ], 
    "537.0": [
      513
    ], 
    "538.0": [
      3307
    ], 
    "541.0": [
      87
    ], 
    "545.0": [
      85
    ], 
    "546.0": [
      102
    ], 
    "547.0": [
      3372
    ], 
    "548.0": [
      143
    ], 
    "551.0": [
      186
    ], 
    "552.0": [
      142
    ], 
    "554.0": [
      226
    ], 
    "555.0": [
      276
    ], 
    "556.0": [
      105
    ], 
    "560.0": [
      101
    ], 
    "561.0": [
      78
    ], 
    "562.0": [
      183
    ], 
    "570.0": [
      103
    ], 
    "571.0": [
      118
    ], 
    "572.0": [
      108
    ], 
    "573.0": [
      140
    ], 
    "574.0": [
      117
    ], 
    "575.0": [
      121
    ], 
    "576.0": [
      83
    ], 
    "577.0": [
      90
    ], 
    "6.0": [
      292
    ], 
    "7.0": [
      301
    ], 
    "7.1": [
      366
    ], 
    "7.2": [
      340
    ], 
    "7.21": [
      469
    ], 
    "7.22": [
      376
    ], 
    "7.23": [
      367
    ], 
    "7.24": [
      339
    ], 
    "7.3": [
      372
    ], 
    "7.4": [
      365
    ], 
    "8.0": [
      208
    ], 
    "8.1": [
      263
    ], 
    "8.2": [
      352
    ], 
    "9.0": [
      350
    ]
  }
}
